{"id": "1405.1346", "review": {"conference": "arxiv", "VERSION": "v1", "DATE_OF_SUBMISSION": "6-May-2014", "title": "Automatic Method Of Domain Ontology Construction based on Characteristics of Corpora POS-Analysis", "abstract": "It is now widely accepted that ontology is one of the fundamental cornerstones of knowledge-based systems, but what is missing is a currently accepted strategy for how ontology can be built; what types of resources and techniques are indispensable to optimize the cost and time on the one hand, and the amplitude, completeness and robustness of ontology on the other. It provides a semi-automated ontology construction method of text corpora in the field of radiation protection, which consists of the following steps: 1) text annotation with part-of-speech tags; 2) disclosure of the significant linguistic structures and formation of the templates; 3) search for text fragments corresponding to these templates; 4) basic ontological instantiation process", "histories": [["v1", "Tue, 6 May 2014 16:28:16 GMT  (328kb)", "http://arxiv.org/abs/1405.1346v1", "XV International Conference, France (2012), in Russian"]], "COMMENTS": "XV International Conference, France (2012), in Russian", "reviews": [], "SUBJECTS": "cs.CL", "authors": ["olena orobinska"], "accepted": false, "id": "1405.1346"}, "pdf": {"name": "1405.1346.pdf", "metadata": {"source": "META", "title": "\u041c\u0435\u0442\u043e\u0434 \u0430\u0432\u0442\u043e\u043c\u0430\u0442\u0438\u0447\u0435\u0441\u043a\u043e\u0433\u043e \u043f\u043e\u0441\u0442\u0440\u043e\u0435\u043d\u0438\u044f \u043e\u043d\u0442\u043e\u043b\u043e\u0433\u0438\u0438 \u043f\u0440\u0435\u0434\u043c\u0435\u0442\u043d\u043e\u0438\u0306 \u043e\u0431\u043b\u0430\u0441\u0442\u0438 \u043d\u0430 \u043e\u0441\u043d\u043e\u0432\u0435 \u0430\u043d\u0430\u043b\u0438\u0437\u0430 \u043b\u0438\u043d\u0433\u0432\u0438\u0441\u0442\u0438\u0447\u0435\u0441\u043a\u0438\u0445 \u0445\u0430\u0440\u0430\u043a\u0442\u0435\u0440\u0438\u0441\u0442\u0438\u043a \u0442\u0435\u043a\u0441\u0442\u043e\u0432\u043e\u0433\u043e \u043a\u043e\u0440\u043f\u0443", "authors": ["\u0415.\u0410. \u041e\u0440\u043e\u0431\u0438\u043d\u0441\u043a\u0430\u044f"], "emails": ["Olena.Orobinska@univ-lyon2.fr"], "sections": [{"heading": null, "text": "\u041c\u0435\u0442\u043e\u0434 \u0430\u0432\u0442\u043e\u043c\u0430\u0442\u0438\u0447\u0435\u0441\u043a\u043e\u0433\u043e \u043f\u043e\u0441\u0442\u0440\u043e\u0435\u043d\u0438\u044f \u043e\u043d\u0442\u043e\u043b\u043e\u0433\u0438\u0438\n\u043f\u0440\u0435\u0434\u043c\u0435\u0442\u043d\u043e\u0439 \u043e\u0431\u043b\u0430\u0441\u0442\u0438 \u043d\u0430 \u043e\u0441\u043d\u043e\u0432\u0435 \u0430\u043d\u0430\u043b\u0438\u0437\u0430 \u043b\u0438\u043d\u0433\u0432\u0438\u0441\u0442\u0438\u0447\u0435\u0441\u043a\u0438\u0445\n\u0445\u0430\u0440\u0430\u043a\u0442\u0435\u0440\u0438\u0441\u0442\u0438\u043a \u0442\u0435\u043a\u0441\u0442\u043e\u0432\u043e\u0433\u043e \u043a\u043e\u0440\u043f\u0443\u0441\u0430\n\u0415.\u0410. \u041e\u0440\u043e\u0431\u0438\u043d\u0441\u043a\u0430\u044f\n\u041b\u0438\u043e\u043d\u0441\u043a\u0438\u0439 \u0443\u043d\u0438\u0432\u0435\u0440\u0441\u0438\u0442\u0435\u0442 \u041b\u0438\u043e\u043d-2 \u0438\u043c. \u041b\u044e\u043c\u044c\u0435\u0440, \u0424\u0440\u0430\u043d\u0446\u0438\u044f\nOlena.Orobinska@univ-lyon2.fr\n\u0410\u043d\u043d\u043e\u0442\u0430\u0446\u0438\u044f\n\u0412\u044b\u0437\u043e\u0432 \u0441\u0435\u0433\u043e\u0434\u043d\u044f\u0448\u043d\u0435\u0433\u043e \u0434\u043d\u044f,\n\u043e\u0431\u0443\u0441\u043b\u043e\u0432\u043b\u0435\u043d\u043d\u044b\u0439 \u0431\u0443\u0440\u043d\u044b\u043c \u0440\u043e\u0441\u0442\u043e\u043c \u0442\u0435\u043a\u0441\u0442\u043e\u0432\u044b\u0445 \u0445\u0440\u0430\u043d\u0438\u043b\u0438\u0449 \u0432 \u0433\u043b\u043e\u0431\u0430\u043b\u044c\u043d\u043e\u0439 \u0441\u0435\u0442\u0438 \u0418\u043d\u0442\u0435\u0440\u043d\u0435\u0442, \u0437\u0430\u043a\u043b\u044e\u0447\u0430\u0435\u0442\u0441\u044f \u0432 \u0442\u043e\u043c, \u0447\u0442\u043e\u0431\u044b \u00ab\u043d\u0430\u0443\u0447\u0438\u0442\u044c\u00bb \u0441\u0430\u043c\u0438 \u0438\u043d\u0444\u043e\u0440\u043c\u0430\u0446\u0438\u043e\u043d\u043d\u044b\u0435 \u0441\u0438\u0441\u0442\u0435\u043c\u044b (\u0418\u0421) \u043e\u0431\u043d\u0430\u0440\u0443\u0436\u0438\u0432\u0430\u0442\u044c \u0438 \u043f\u0440\u0430\u0432\u0438\u043b\u044c\u043d\u043e \u0438\u043d\u0442\u0435\u0440\u043f\u0440\u0435\u0442\u0438\u0440\u043e\u0432\u0430\u0442\u044c \u043f\u043e\u043b\u0435\u0437\u043d\u0443\u044e \u0438\u043d\u0444\u043e\u0440\u043c\u0430\u0446\u0438\u044e, \u043f\u0440\u0435\u0434\u043e\u0441\u0442\u0430\u0432\u043b\u044f\u0435\u043c\u0443\u044e \u0442\u0435\u043a\u0441\u0442\u043e\u043c.\n\u0420\u0430\u0437\u0440\u0430\u0431\u043e\u0442\u043a\u0430 \u043c\u0435\u0442\u043e\u0434\u043e\u0432 \u0430\u0432\u0442\u043e\u043c\u0430\u0442\u0438\u0447\u0435\u0441\u043a\u043e\u0433\u043e\n\u0430\u043d\u0430\u043b\u0438\u0437\u0430 \u0442\u0435\u043a\u0441\u0442\u043e\u0432\u043e\u0439 \u0438\u043d\u0444\u043e\u0440\u043c\u0430\u0446\u0438\u0438 \u0438 \u0438\u0437\u0432\u043b\u0435\u0447\u0435\u043d\u0438\u0435 \u0438\u0437 \u043f\u043e\u043b\u043d\u043e\u0442\u0435\u043a\u0441\u0442\u043e\u0432\u044b\u0445 \u0434\u043e\u043a\u0443\u043c\u0435\u043d\u0442\u043e\u0432 \u0440\u0435\u043b\u0435\u0432\u0430\u043d\u0442\u043d\u044b\u0445 \u0434\u0430\u043d\u043d\u044b\u0445 \u044f\u0432\u043b\u044f\u0435\u0442\u0441\u044f \u0430\u043a\u0442\u0443\u0430\u043b\u044c\u043d\u043e\u0439 \u0437\u0430\u0434\u0430\u0447\u0435\u0439 \u0438\u043d\u0436\u0435\u043d\u0435\u0440\u0438\u0438 \u0437\u043d\u0430\u043d\u0438\u0439 \u0432 \u0446\u0435\u043b\u043e\u043c \u0438 \u043e\u043d\u0442\u043e\u043b\u043e\u0433\u0438\u0447\u0435\u0441\u043a\u043e\u0433\u043e \u0438\u043d\u0436\u0438\u043d\u0438\u0440\u0438\u043d\u0433\u0430 \u0432 \u0447\u0430\u0441\u0442\u043d\u043e\u0441\u0442\u0438. \u041f\u0440\u0435\u0434\u043f\u043e\u0441\u044b\u043b\u043a\u043e\u0439 \u043f\u043e\u044f\u0432\u043b\u0435\u043d\u0438\u044f \u043f\u0440\u043e\u0440\u044b\u0432\u043d\u044b\u0445 \u0442\u0435\u0445\u043d\u043e\u043b\u043e\u0433\u0438\u0439, \u043a\u043e\u0442\u043e\u0440\u044b\u0435 \u043f\u043e\u0437\u0432\u043e\u043b\u0438 \u0431\u044b \u0435\u0435 \u0440\u0435\u0448\u0438\u0442\u044c \u0430\u0432\u0442\u043e\u0440 \u0441\u0447\u0438\u0442\u0430\u0435\u0442 \u043f\u043e\u0438\u0441\u043a \u0440\u0435\u0448\u0435\u043d\u0438\u0439 \u043d\u0430 \u043e\u0441\u043d\u043e\u0432\u0435 \u043c\u0435\u0442\u043e\u0434\u043e\u0432 \u0441\u0438\u0441\u0442\u0435\u043c\u043d\u043e\u0433\u043e \u0430\u043d\u0430\u043b\u0438\u0437\u0430, \u043a\u0430\u043a \u0441\u0430\u043c\u043e\u0433\u043e\n\u043e\u0431\u044a\u0435\u043a\u0442\u0430 \u0438\u0441\u0441\u043b\u0435\u0434\u043e\u0432\u0430\u043d\u0438\u044f  \u0442\u0435\u043a\u0441\u0442\u0430, \u0442\u0430\u043a \u0438 \u043f\u043e\u0441\u0442\u0430\u0432\u043b\u0435\u043d\u043d\u044b\u0445 \u043f\u0440\u0438\u043a\u043b\u0430\u0434\u043d\u044b\u0445 \u0437\u0430\u0434\u0430\u0447, \u043a\u043e\u0442\u043e\u0440\u044b\u0435 \u0434\u043e\u043b\u0436\u043d\u044b \u0431\u044b\u0442\u044c \u0440\u0435\u0448\u0435\u043d\u044b \u0432 \u0440\u0435\u0437\u0443\u043b\u044c\u0442\u0430\u0442\u0435 \u0442\u0430\u043a\u043e\u0439 \u043e\u0431\u0440\u0430\u0431\u043e\u0442\u043a\u0438. \u0418\u043d\u044b\u043c\u0438 \u0441\u043b\u043e\u0432\u0430\u043c\u0438, \u0434\u043b\u044f \u0441\u0435\u043c\u0430\u043d\u0442\u0438\u0447\u0435\u0441\u043a\u043e\u0433\u043e \u0430\u043d\u0430\u043b\u0438\u0437\u0430 \u0442\u0435\u043a\u0441\u0442\u043e\u0432\u043e\u0439 \u0438\u043d\u0444\u043e\u0440\u043c\u0430\u0446\u0438\u0438 \u0442\u0440\u0435\u0431\u0443\u0435\u0442\u0441\u044f \u043e\u043d\u0442\u043e\u043b\u043e\u0433\u0438\u0447\u0435\u0441\u043a\u0438\u0439 \u043f\u043e\u0434\u0445\u043e\u0434, \u0442.\u0435. \u0447\u0442\u043e\u0431\u044b \u043e\u0431\u043d\u0430\u0440\u0443\u0436\u0438\u0442\u044c \u0432 \u0442\u0435\u043a\u0441\u0442\u0435 \u0442\u0440\u0435\u0431\u0443\u0435\u043c\u0443\u044e \u0438\u043d\u0444\u043e\u0440\u043c\u0430\u0446\u0438\u044e, \u0441\u0430\u043c\u0430 \u0418\u0421 \u0434\u043e\u043b\u0436\u043d\u0430 \u043e\u0431\u043b\u0430\u0434\u0430\u0442\u044c \u0434\u043e\u0441\u0442\u0430\u0442\u043e\u0447\u043d\u044b\u043c \u043e\u0431\u044a\u0435\u043c\u043e\u043c \u043b\u0438\u043d\u0433\u0432\u0438\u0441\u0442\u0438\u0447\u0435\u0441\u043a\u0438\u0445 \u0437\u043d\u0430\u043d\u0438\u0439.\n\u0412\u0432\u0435\u0434\u0435\u043d\u0438\u0435\n\u0421\u043e \u0441\u0441\u044b\u043b\u043a\u043e\u0439 \u043d\u0430 [2],[3] \u043c\u043e\u0436\u043d\u043e \u0443\u0442\u0432\u0435\u0440\u0436\u0434\u0430\u0442\u044c, \u0447\u0442\u043e \u0432\n2011 \u0433. \u043d\u0430\u0438\u0431\u043e\u043b\u0435\u0435 \u0431\u044b\u0441\u0442\u0440\u043e \u0440\u0430\u0441\u0442\u0443\u0449\u0435\u0439 \u043a\u0430\u0442\u0435\u0433\u043e\u0440\u0438\u0435\u0439 \u0442. \u043d\u0430\u0437. \u201csweet tools\u201d \u0438\u043b\u0438 \u0438\u043d\u0442\u0435\u043b\u043b\u0435\u043a\u0442\u0443\u0430\u043b\u044c\u043d\u044b\u0445 \u0441\u0438\u0441\u0442\u0435\u043c \u0431\u044b\u043b\u0438 \u0438\u043c\u0435\u043d\u043d\u043e \u043e\u043d\u0442\u043e\u043b\u043e\u0433\u0438\u0438. \u041e\u0431\u043e\u0431\u0449\u0430\u044f \u043c\u043d\u043e\u0436\u0435\u0441\u0442\u0432\u043e \u0441\u0445\u043e\u0434\u043d\u044b\u0445 \u043e\u043f\u0440\u0435\u0434\u0435\u043b\u0435\u043d\u0438\u0439, \u043d\u0430\u043f\u043e\u043c\u043d\u0438\u043c, \u0447\u0442\u043e \u0432 \u043d\u0430\u0441\u0442\u043e\u044f\u0449\u0435\u0435 \u0432\u0440\u0435\u043c\u044f \u043f\u043e\u0434 \u043e\u043d\u0442\u043e\u043b\u043e\u0433\u0438\u0435\u0439 \u043f\u043e\u0434\u0440\u0430\u0437\u0443\u043c\u0430\u0435\u0432\u0430\u0435\u0442\u0441\u044f \u0441\u0435\u043c\u0430\u043d\u0442\u0438\u0447\u0435\u0441\u043a\u0430\u044f \u0441\u0442\u0440\u0443\u043a\u0442\u0443\u0440\u0430, \u0432 \u044f\u0432\u043d\u043e\u043c \u0432\u0438\u0434\u0435 \u043e\u043f\u0438\u0441\u044b\u0432\u0430\u044e\u0449\u0430\u044f \u043e\u0441\u043d\u043e\u0432\u043d\u044b\u0435 \u043f\u043e\u043d\u044f\u0442\u0438\u044f (\u043a\u043e\u043d\u0446\u0435\u043f\u0442\u044b) \u043f\u0440\u0435\u0434\u043c\u0435\u0442\u043d\u043e\u0439 \u043e\u0431\u043b\u0430\u0441\u0442\u0438 (\u041f\u041e), \u0441\u0432\u044f\u0437\u044b\u0432\u0430\u044e\u0449\u0438\u0435 \u0438\u0445 \u043e\u0442\u043d\u043e\u0448\u0435\u043d\u0438\u044f, \u0430 \u0442\u0430\u043a\u0436\u0435 \u0430\u043a\u0441\u0438\u043e\u043c\u044b, \u043e\u043f\u0438\u0441\u044b\u0432\u0430\u044e\u0449\u0438\u0435 \u043f\u0440\u0430\u0432\u0438\u043b\u0430 \u0432\u044b\u0432\u043e\u0434\u0430 \u043d\u043e\u0432\u044b\u0445 \u043a\u043e\u043d\u0446\u0435\u043f\u0442\u043e\u0432 [4].\n\u0414\u043e \u0441\u0438\u0445 \u043f\u043e\u0440, \u043f\u043e\u0441\u0442\u0440\u043e\u0435\u043d\u0438\u0435 \u043e\u043d\u0442\u043e\u043b\u043e\u0433\u0438\u0438 \u043e\u0441\u0442\u0430\u0435\u0442\u0441\u044f \u043f\u0440\u0438\u043e\u0440\u0438\u0442\u0435\u0442\u043d\u043e\u0439 \u0437\u0430\u0434\u0430\u0447\u0435\u0439 \u044d\u043a\u0441\u043f\u0435\u0440\u0442\u043e\u0432 \u041f\u041e, \u0447\u0442\u043e \u0434\u0435\u043b\u0430\u0435\u0442 \u044d\u0442\u043e\u0442 \u043f\u0440\u043e\u0446\u0435\u0441\u0441 \u043e\u0447\u0435\u043d\u044c \u0434\u043e\u0440\u043e\u0433\u043e\u0441\u0442\u044f\u0449\u0438\u043c \u0438 \u0434\u043e\u043b\u0433\u043e\u0441\u0440\u043e\u0447\u043d\u044b\u043c.\n\u0418\u043c\u0435\u043d\u043d\u043e \u044d\u0442\u0438\u043c\u0438 \u0444\u0430\u043a\u0442\u043e\u0440\u0430\u043c\u0438 \u043e\u0431\u044a\u044f\u0441\u043d\u044f\u0435\u0442\u0441\u044f \u0431\u043e\u043b\u044c\u0448\u043e\u0435 \u043a\u043e\u043b\u0438\u0447\u0435\u0441\u0442\u0432\u043e \u0440\u0430\u0431\u043e\u0442, \u043f\u043e\u044f\u0432\u0438\u0432\u0448\u0438\u0445\u0441\u044f \u0432 \u043f\u043e\u0441\u043b\u0435\u0434\u043d\u0435\u0435 \u0432\u0440\u0435\u043c\u044f \u0438 \u043f\u0440\u0435\u0434\u043b\u0430\u0433\u0430\u044e\u0449\u0438\u0445 \u043d\u043e\u0432\u044b\u0435 \u043c\u0435\u0442\u043e\u0434\u044b \u0430\u043d\u0430\u043b\u0438\u0437\u0430 \u0442\u0435\u043a\u0441\u0442\u0430 \u0438, \u043d\u0430 \u0438\u0445 \u043e\u0441\u043d\u043e\u0432\u0435, \u0442\u0435\u0445\u043d\u043e\u043b\u043e\u0433\u0438\u0438 \u0430\u0432\u0442\u043e\u043c\u0430\u0442\u0438\u0437\u0438\u0440\u043e\u0432\u0430\u043d\u043d\u043e\u0433\u043e \u043f\u043e\u0441\u0442\u0440\u043e\u0435\u043d\u0438\u044f \u043e\u043d\u0442\u043e\u043b\u043e\u0433\u0438\u0439 [2].\n\u0414\u043e \u043d\u0430\u0447\u0430\u043b\u0430 2000\u2013\u043d\u044b\u0445 \u0433\u043e\u0434\u043e\u0432 \u0434\u043b\u044f \u0440\u0435\u0448\u0435\u043d\u0438\u044f \u0437\u0430\u0434\u0430\u0447 \u0430\u043d\u0430\u043b\u0438\u0437\u0430 \u0442\u0435\u043a\u0441\u0442\u0430 \u0432 \u043e\u0441\u043d\u043e\u0432\u043d\u043e\u043c \u043f\u0440\u0438\u043c\u0435\u043d\u044f\u043b\u0438\u0441\u044c \u0438 \u0440\u0430\u0437\u0432\u0438\u0432\u0430\u043b\u0438\u0441\u044c \u0441\u0442\u0430\u0442\u0438\u0441\u0442\u0438\u0447\u0435\u0441\u043a\u0438\u0435 \u043c\u0435\u0442\u043e\u0434\u044b. \u0421 \u043f\u043e\u044f\u0432\u043b\u0435\u043d\u0438\u0435\u043c \u0441\u0435\u0442\u0435\u0432\u044b\u0445 \u043b\u0435\u043a\u0441\u0438\u0447\u0435\u0441\u043a\u0438\u0445 \u0440\u0435\u0441\u0443\u0440\u0441\u043e\u0432 \u0438 \u0441\u043e\u0432\u0435\u0440\u0448\u0435\u043d\u0441\u0442\u0432\u043e\u0432\u0430\u043d\u0438\u0435\u043c \u0441\u0438\u043d\u0442\u0430\u043a\u0441\u0438\u0447\u0435\u0441\u043a\u0438\u0445 \u0430\u043d\u0430\u043b\u0438\u0437\u0430\u0442\u043e\u0440\u043e\u0432 \u043b\u0438\u043d\u0432\u0438\u0441\u0442\u0438\u0447\u0435\u0441\u043a\u0438\u0435 \u043c\u0435\u0442\u043e\u0434\u044b \u043f\u0440\u0438\u0432\u043b\u0435\u043a\u0430\u044e\u0442 \u0432\u0441\u0435 \u0431\u043e\u043b\u044c\u0448\u0435\u0435 \u0432\u043d\u0438\u043c\u0430\u043d\u0438\u0435 \u0441\u043f\u0435\u0446\u0438\u0430\u043b\u0438\u0441\u0442\u043e\u0432 \u0431\u043b\u0430\u0433\u043e\u0434\u0430\u0440\u044f \u0432\u044b\u0441\u043e\u043a\u043e\u043c\u0443 \u043a\u0430\u0447\u0435\u0441\u0442\u0432\u0443 \u0440\u0435\u0437\u0443\u043b\u044c\u0442\u0430\u0442\u043e\u0432, \u043a\u043e\u0442\u043e\u0440\u044b\u0435 \u043e\u0431\u0435\u0449\u0430\u044e\u0442 \u0442\u0430\u043a\u0438\u0435 \u043c\u0435\u0442\u043e\u0434\u044b [5]. \u041f\u043e\u044d\u0442\u043e\u043c\u0443 \u0446\u0435\u043b\u044c\u044e \u0434\u0430\u043d\u043d\u043e\u0439 \u0440\u0430\u0431\u043e\u0442\u044b \u044f\u0432\u043b\u044f\u0435\u0442\u0441\u044f \u043e\u043f\u0438\u0441\u0430\u043d\u0438\u0435 \u0441\u0442\u0440\u0443\u043a\u0442\u0443\u0440\u044b \u0418\u0421, \u043f\u043e\u0437\u0432\u043e\u043b\u044f\u044e\u0449\u0435\u0439\n\u043e\u0431\u043d\u0430\u0440\u0443\u0436\u0438\u0432\u0430\u0442\u044c \u0432 \u0442\u0435\u043a\u0441\u0442\u043e\u0432\u043e\u043c \u043a\u043e\u0440\u043f\u0443\u0441\u0435 \u0440\u0435\u043b\u0435\u0432\u0430\u043d\u0442\u043d\u044b\u0435 \u043a\u043e\u043d\u0446\u0435\u043f\u0442\u044b \u041f\u041e (\u0440\u0430\u0434\u0438\u0430\u0446\u0438\u043e\u043d\u043d\u0430\u044f \u0437\u0430\u0449\u0438\u0442\u0430) \u043d\u0430 \u043e\u0441\u043d\u043e\u0432\u0435 \u0438\u0441\u043f\u043e\u043b\u044c\u0437\u043e\u0432\u0430\u043d\u0438\u044f \u043b\u0438\u043d\u0433\u0432\u0438\u0441\u0442\u0438\u0447\u0435\u0441\u043a\u0438\u0445 \u0448\u0430\u0431\u043b\u043e\u043d\u043e\u0432, \u0445\u0430\u0440\u0430\u043a\u0442\u0435\u0440\u043d\u044b\u0445 \u0434\u043b\u044f \u0434\u0430\u043d\u043d\u043e\u0439 \u041f\u041e.\n\u041e\u0441\u043d\u043e\u0432\u043d\u044b\u0435 \u043f\u0440\u0438\u043d\u0446\u0438\u043f\u044b \u043f\u043e\u0441\u0442\u0440\u043e\u0435\u043d\u0438\u044f\n\u043e\u043d\u0442\u043e\u043b\u043e\u0433\u0438\u0439\n\u0410\u0432\u0442\u043e\u0440 \u0432 \u043e\u0441\u043d\u043e\u0432\u043d\u043e\u043c \u0440\u0430\u0437\u0434\u0435\u043b\u044f\u0435\u0442 \u043f\u043e\u0434\u0445\u043e\u0434 \u043a \u043f\u043e\u0441\u0442\u0440\u043e\u0435\u043d\u0438\u044e \u043e\u043d\u0442\u043e\u043b\u043e\u0433\u0438\u0438 \u043d\u0430 \u043e\u0441\u043d\u043e\u0432\u0435 \u0442\u0435\u043a\u0441\u0442\u0430, \u043f\u0440\u0435\u0434\u043b\u043e\u0436\u0435\u043d\u043d\u044b\u0439 Buitelaar \u0438 \u043a\u043e\u043b\u043b\u0435\u0433\u0430\u043c\u0438 \u0432 2005 \u0433. [6], \u0438\u0437\u0432\u0435\u0441\u0442\u043d\u044b\u0439 \u043a\u0430\u043a Layer Cake. \u0412\u0435\u0441\u044c \u043f\u0440\u043e\u0446\u0435\u0441\u0441 \u043f\u043e\u0441\u0442\u0440\u043e\u0435\u043d\u0438\u044f \u043e\u043d\u0442\u043e\u043b\u043e\u0433\u0438\u0438 \u0440\u0430\u0437\u0431\u0438\u0442 \u043d\u0430 \u043d\u0435\u0441\u043a\u043e\u043b\u044c\u043a\u043e \u043d\u0435\u0437\u0430\u0432\u0438\u0441\u0438\u043c\u044b\u0445 \u044d\u0442\u0430\u043f\u043e\u0432, \u043d\u0430 \u043a\u0430\u0436\u0434\u043e\u043c \u0438\u0437 \u043a\u043e\u0442\u043e\u0440\u044b\u0445 \u0440\u0435\u0448\u0430\u0435\u0442\u0441\u044f \u043e\u0434\u043d\u0430 \u043e\u043f\u0440\u0435\u0434\u0435\u043b\u0435\u043d\u043d\u0430\u044f \u0437\u0430\u0434\u0430\u0447\u0430, \u0440\u0435\u0437\u0443\u043b\u044c\u0442\u0430\u0442\u044b \u043a\u043e\u0442\u043e\u0440\u043e\u0439, \u0432 \u0441\u0432\u043e\u044e \u043e\u0447\u0435\u0440\u0435\u0434\u044c, \u0441\u043b\u0443\u0436\u0430\u0442\n\u0438\u0441\u0445\u043e\u0434\u043d\u044b\u043c\u0438 \u0434\u0430\u043d\u043d\u044b\u043c\u0438 \u0434\u043b\u044f \u0437\u0430\u0434\u0430\u0447\u0438 \u0441\u043b\u0435\u0434\u0443\u044e\u0449\u0435\u0433\u043e, \u043a\u0430\u043a \u043f\u0440\u0430\u0432\u0438\u043b\u043e, \u0431\u043e\u043b\u0435\u0435 \u0441\u043b\u043e\u0436\u043d\u043e\u0433\u043e \u0443\u0440\u043e\u0432\u043d\u044f. \u0421\u043e\u0433\u043b\u0430\u0441\u043d\u043e \u044d\u0442\u043e\u043c\u0443 \u043f\u043e\u0434\u0445\u043e\u0434\u0443 \u043c\u043e\u0436\u043d\u043e \u0432\u044b\u0434\u0435\u043b\u0438\u0442\u044c \u0441\u043b\u0435\u0434\u0443\u044e\u0449\u0443\u044e \u043f\u043e\u0441\u043b\u0435\u0434\u043e\u0432\u0430\u0442\u0435\u043b\u044c\u043d\u043e\u0441\u0442\u044c \u0434\u0435\u0439\u0441\u0442\u0432\u0438\u0439: \u0438\u0437\u0432\u043b\u0435\u0447\u0435\u043d\u0438\u0435 \u0438\u0437 \u0442\u0435\u043a\u0441\u0442\u0430\n\u0442\u0435\u0440\u043c\u0438\u043d\u043e\u0432-\u043a\u0430\u043d\u0434\u0438\u0434\u0430\u0442\u043e\u0432  \u0440\u0430\u0437\u0431\u0438\u0435\u043d\u0438\u0435 \u0442\u0435\u0440\u043c\u0438\u043d\u043e\u0432 \u043d\u0430\n\u0433\u0440\u0443\u043f\u043f\u044b (\u043a\u043b\u0430\u0441\u0442\u0435\u0440\u0438\u0437\u0430\u0446\u0438\u044f)  \u043f\u0440\u0438\u0441\u0432\u043e\u0435\u043d\u0438\u0435\n\u043e\u0431\u043e\u0431\u0449\u0430\u044e\u0449\u0435\u0433\u043e \u043f\u043e\u043d\u044f\u0442\u0438\u044f-\u043a\u043e\u043d\u0446\u0435\u043f\u0442\u0430 \u043a\u0430\u0436\u0434\u043e\u0439 \u0433\u0440\u0443\u043f\u043f\u0435 \n\u043e\u043f\u0440\u0435\u0434\u0435\u043b\u0435\u043d\u0438\u0435 \u043e\u0442\u043d\u043e\u0448\u0435\u043d\u0438\u0439 \u043c\u0435\u0436\u0434\u0443 \u043a\u043e\u043d\u0446\u0435\u043f\u0442\u0430\u043c\u0438  \u0444\u043e\u0440\u043c\u0438\u0440\u043e\u0432\u0430\u043d\u0438\u0435 \u043f\u0440\u0430\u0432\u0438\u043b \u0432\u044b\u0432\u043e\u0434\u0430 (\u0440\u0430\u0441\u0448\u0438\u0440\u0435\u043d\u0438\u044f \u043a\u043e\u043d\u0446\u0435\u043f\u0442\u043e\u0432). \u0414\u043b\u044f \u043d\u0430\u0447\u0430\u043b\u044c\u043d\u044b\u0445 \u044d\u0442\u0430\u043f\u043e\u0432 \u043c\u043d\u043e\u0433\u043e\u0447\u0438\u0441\u043b\u0435\u043d\u043d\u044b\u0435 \u0441\u0442\u0430\u0442\u0438\u0441\u0442\u0438\u0447\u0435\u0441\u043a\u0438\u0435 \u043c\u0435\u0442\u043e\u0434\u044b \u043f\u043e\u0437\u0432\u043e\u043b\u044f\u044e\u0442 \u043f\u043e\u043b\u0443\u0447\u0430\u0442\u044c \u0432\u0435\u0441\u044c\u043c\u0430 \u043a\u0430\u0447\u0435\u0441\u0442\u0432\u0435\u043d\u043d\u044b\u0435 \u0440\u0435\u0437\u0443\u043b\u044c\u0442\u0430\u0442\u044b (\u0434\u043e 90% \u0442\u043e\u0447\u043d\u043e\u0441\u0442\u0438 \u043f\u043e \u0441\u0440\u0430\u0432\u043d\u0435\u043d\u0438\u044e \u0441 \u0440\u0435\u0437\u0443\u043b\u044c\u0442\u0430\u0442\u0430\u043c\u0438 \u0440\u0430\u0431\u043e\u0442\u044b \u044d\u043a\u0441\u043f\u0435\u0440\u0442\u043e\u0432 [7]). \u0422\u0440\u0443\u0434\u044b XV \u0412\u0441\u0435\u0440\u043e\u0441\u0441\u0438\u0439\u0441\u043a\u043e\u0439 \u043e\u0431\u044a\u0435\u0434\u0438\u043d\u0435\u043d\u043d\u043e\u0439 \u043a\u043e\u043d\u0444\u0435\u0440\u0435\u043d\u0446\u0438\u0438 \u00ab\u0418\u043d\u0442\u0435\u0440\u043d\u0435\u0442 \u0438 \u0441\u043e\u0432\u0440\u0435\u043c\u0435\u043d\u043d\u043e\u0435 \u043e\u0431\u0449\u0435\u0441\u0442\u0432\u043e\u00bb (IMS-2012), \u0421\u0430\u043d\u043a\u0442-\u041f\u0435\u0442\u0435\u0440\u0431\u0443\u0440\u0433, \u0420\u043e\u0441\u0441\u0438\u044f, 2012.\n\u041e\u0434\u043d\u0430\u043a\u043e \u0434\u043b\u044f \u043f\u043e\u0441\u0442\u0440\u043e\u0435\u043d\u0438\u044f \u0442\u0430\u043a\u0441\u043e\u043d\u043e\u043c\u0438\u0438 \u043f\u043e\u043d\u044f\u0442\u0438\u0439 \u0438\n\u043e\u0431\u043d\u0430\u0440\u0443\u0436\u0435\u043d\u0438\u044f \u043d\u0435\u0442\u043a\u0430\u0441\u043e\u043d\u043e\u043c\u0438\u0447\u0435\u0441\u043a\u0438\u0445 \u043e\u0442\u043d\u043e\u0448\u0435\u043d\u0438\u0439 \u043d\u0435\u043e\u0431\u0445\u043e\u0434\u0438\u043c\u0430 \u0440\u0430\u0437\u0440\u0430\u0431\u043e\u0442\u043a\u0430 \u043b\u0438\u043d\u0433\u0432\u0438\u0441\u0442\u0438\u0447\u0435\u0441\u043a\u0438\u0445 \u043c\u0435\u0442\u043e\u0434\u043e\u0432. \u0412\n\u0447\u0430\u0441\u0442\u043d\u043e\u0441\u0442\u0438, \u043e\u0434\u043d\u0438\u043c \u0438\u0437 \u044d\u0444\u0444\u0435\u043a\u0442\u0438\u0432\u043d\u044b\u0445 \u043f\u043e\u0434\u0445\u043e\u0434\u043e\u0432 \u0434\u043b\u044f\n\u043e\u0431\u043d\u0430\u0440\u0443\u0436\u0435\u043d\u0438\u044f \u0433\u0440\u0443\u043f\u043f\u044b \u0441\u0438\u043d\u043e\u043d\u0438\u043c\u043e\u0432 \u0438 \u043e\u0431\u0449\u0435\u0433\u043e \u0434\u043b\u044f \u043d\u0438\u0445 \u0433\u0438\u043f\u0435\u0440\u043e\u043d\u0438\u043c\u0430 \u044f\u0432\u043b\u044f\u0435\u0442\u0441\u044f \u0438\u0441\u043f\u043e\u043b\u044c\u0437\u043e\u0432\u0430\u043d\u0438\u0435\n\u043b\u0438\u043d\u0433\u0432\u0438\u0441\u0442\u0438\u0447\u0435\u0441\u043a\u0438\u0445 \u0448\u0430\u0431\u043b\u043e\u043d\u043e\u0432, \u043f\u0440\u0435\u0434\u043b\u043e\u0436\u0435\u043d\u043d\u044b\u0445 \u0435\u0449\u0435 M. Hearst [8]. \u0414\u0430\u043b\u044c\u043d\u0435\u0439\u0448\u0435\u0435 \u0441\u043e\u0432\u0435\u0440\u0448\u0435\u043d\u0441\u0442\u0432\u043e\u0432\u0430\u043d\u0438\u0435 \u0442\u0430\u043a\u043e\u0433\u043e \u043f\u043e\u0434\u0445\u043e\u0434\u0430 \u0437\u0430\u0432\u0438\u0441\u0438\u0442 \u043e\u0442 \u043d\u0430\u043b\u0438\u0447\u0438\u044f \u043e\u0431\u0449\u0435\u0439 \u0442\u0435\u043e\u0440\u0438\u0438 \u043e\u043f\u0438\u0441\u0430\u043d\u0438\u044f \u0438 \u0430\u043d\u0430\u043b\u0438\u0437\u0430 \u043a\u043e\u043d\u043a\u0440\u0435\u0442\u043d\u043e\u0433\u043e \u044f\u0437\u044b\u043a\u0430. \u0412 \u044d\u0442\u043e\u0439 \u0441\u0432\u044f\u0437\u0438 \u0430\u0432\u0442\u043e\u0440 \u0440\u0430\u0437\u0434\u0435\u043b\u044f\u0435\u0442 \u0438\u0434\u0435\u044e \u0417\u043e\u043b\u043e\u0442\u043e\u0432\u043e\u0439 \u0413. \u0410. \u043e \u0442\u043e\u043c, \u0447\u0442\u043e \u0441\u0438\u043d\u0442\u0430\u043a\u0441\u0438\u0447\u0435\u0441\u043a\u0438\u0439 \u0441\u0442\u0440\u043e\u0439 \u0440\u0435\u0447\u0438 (\u0442\u0435\u043a\u0441\u0442\u0430) \u043e\u0440\u0433\u0430\u043d\u0438\u0437\u0443\u0435\u0442\u0441\u044f \u0440\u0435\u0433\u0443\u043b\u044f\u0440\u043d\u044b\u043c\u0438 \u043a\u043e\u043c\u0431\u0438\u043d\u0430\u0446\u0438\u044f\u043c\u0438 \u00ab\u044d\u043b\u0435\u043c\u0435\u043d\u0442\u0430\u0440\u043d\u044b\u0445\u00bb \u0435\u0434\u0438\u043d\u0438\u0446, \u0438\u0437 \u043a\u043e\u0442\u043e\u0440\u044b\u0445 \u0441\u0442\u0440\u043e\u044f\u0442\u0441\u044f \u0432\u0441\u0435 \u0434\u0440\u0443\u0433\u0438\u0435 \u0431\u043e\u043b\u0435\u0435 \u0441\u043b\u043e\u0436\u043d\u044b\u0435 (\u0440\u0435\u0447\u0435\u0432\u044b\u0435 \u0438\u043b\u0438 \u0442\u0435\u043a\u0441\u0442\u043e\u0432\u044b\u0435) \u043a\u043e\u043d\u0441\u0442\u0440\u0443\u043a\u0446\u0438\u0438 [9]. \u0412 \u043a\u0430\u0447\u0435\u0441\u0442\u0432\u0435 \u0442\u0430\u043a\u043e\u0439 \u0435\u0434\u0438\u043d\u0438\u0446\u044b \u0432\u044b\u0434\u0432\u0438\u043d\u0443\u0442\u043e \u043f\u043e\u043d\u044f\u0442\u0438\u0435 \u0441\u0438\u043d\u0442\u0430\u043a\u0441\u0435\u043c\u044b. \u0421\u0438\u043d\u0442\u0430\u043a\u0441\u0435\u043c\u043e\u0439 \u043f\u043e \u0417\u043e\u043b\u043e\u0442\u043e\u0432\u043e\u0439 \u0413.\u0410. \u043d\u0430\u0437\u044b\u0432\u0430\u0435\u0442\u0441\u044f \u043c\u0438\u043d\u0438\u043c\u0430\u043b\u044c\u043d\u0430\u044f \u0434\u0430\u043b\u0435\u0435 \u043d\u0435\u0434\u0435\u043b\u0438\u043c\u0430\u044f \u0441\u0435\u043c\u0430\u043d\u0442\u0438\u043a\u043e-\u0441\u0438\u043d\u0442\u0430\u043a\u0441\u0438\u0447\u0435\u0441\u043a\u0430\u044f \u0435\u0434\u0438\u043d\u0438\u0446\u0430 \u0440\u0443\u0441\u0441\u043a\u043e\u0433\u043e \u044f\u0437\u044b\u043a\u0430,\n\u0432\u044b\u0441\u0442\u0443\u043f\u0430\u044e\u0449\u0430\u044f \u043e\u0434\u043d\u043e\u0432\u0440\u0435\u043c\u0435\u043d\u043d\u043e \u0438 \u043a\u0430\u043a \u043d\u043e\u0441\u0438\u0442\u0435\u043b\u044c \u044d\u043b\u0435\u043c\u0435\u043d\u0442\u0430\u0440\u043d\u043e\u0433\u043e \u0441\u043c\u044b\u0441\u043b\u0430, \u0438 \u043a\u0430\u043a \u043a\u043e\u043d\u0441\u0442\u0440\u0443\u043a\u0442\u0438\u0432\u043d\u044b\u0439 \u043a\u043e\u043c\u043f\u043e\u043d\u0435\u043d\u0442 \u0441 \u0444\u0443\u043d\u043a\u0446\u0438\u043e\u043d\u0430\u043b\u044c\u043d\u043e\u0441\u0442\u044c\u044e, \u043d\u0435\u043e\u0431\u0445\u043e\u0434\u0438\u043c\u043e\u0439 \u0438 \u0434\u043e\u0441\u0442\u0430\u0442\u043e\u0447\u043d\u043e\u0439 \u0434\u043b\u044f \u043f\u043e\u0441\u0442\u0440\u043e\u0435\u043d\u0438\u044f \u0431\u043e\u043b\u0435\u0435 \u0441\u043b\u043e\u0436\u043d\u044b\u0445 \u0441\u0438\u043d\u0442\u0430\u043a\u0441\u0438\u0447\u0435\u0441\u043a\u0438\u0445 \u043a\u043e\u043d\u0441\u0442\u0440\u0443\u043a\u0446\u0438\u0439.\n\u041f\u0440\u0438\u0437\u043d\u0430\u043a\u0430\u043c\u0438 \u0441\u0438\u043d\u0442\u0430\u043a\u0441\u0435\u043c\u044b \u0441\u043b\u0443\u0436\u0430\u0442: 1) \u043a\u0430\u0442\u0435\u0433\u043e\u0440\u0438\u0430\u043b\u044c\u043d\u043e\u0435 \u0437\u043d\u0430\u0447\u0435\u043d\u0438\u0435 \u0441\u043b\u043e\u0432\u0430, \u043e\u0442 \u043a\u043e\u0442\u043e\u0440\u043e\u0433\u043e \u043e\u043d\u0430 \u043e\u0431\u0440\u0430\u0437\u043e\u0432\u0430\u043d\u0430, 2) \u043e\u043f\u0440\u0435\u0434\u0435\u043b\u0435\u043d\u043d\u0430\u044f (\u043a\u043e\u043d\u043a\u0440\u0435\u0442\u043d\u0430\u044f) \u043c\u043e\u0440\u0444\u043e\u043b\u043e\u0433\u0438\u0447\u0435\u0441\u043a\u0430\u044f \u0444\u043e\u0440\u043c\u0430, 3) \u0444\u0443\u043d\u043a\u0446\u0438\u043e\u043d\u0430\u043b\u044c\u043d\u043e\u0441\u0442\u044c, \u0432\u044b\u0442\u0435\u043a\u0430\u044e\u0449\u0430\u044f \u0438\u0437 \u0434\u0432\u0443\u0445 \u043f\u0435\u0440\u0432\u044b\u0445 \u043f\u0440\u0438\u0437\u043d\u0430\u043a\u043e\u0432, \u043a\u0430\u043a \u0441\u043f\u043e\u0441\u043e\u0431\u043d\u043e\u0441\u0442\u044c \u0440\u0435\u0430\u043b\u0438\u0437\u043e\u0432\u044b\u0432\u0430\u0442\u044c\u0441\u044f \u0432 \u043e\u043f\u0440\u0435\u0434\u0435\u043b\u0435\u043d\u043d\u044b\u0445 \u043f\u043e\u0437\u0438\u0446\u0438\u044f\u0445 (\u0440\u0435\u0447\u0438, \u0442\u0435\u0441\u0442\u0430), \u0442.\u0435. \u043a\u0430\u043a \u0432\u043e\u0437\u043c\u043e\u0436\u043d\u0430\u044f \u0440\u043e\u043b\u044c \u0432 \u043f\u043e\u0441\u0442\u0440\u043e\u0435\u043d\u0438\u0438 \u043a\u043e\u043c\u043c\u0443\u043d\u0438\u043a\u0430\u0442\u0438\u0432\u043d\u043e\u0439 \u0435\u0434\u0438\u043d\u0438\u0446\u044b. \u0417\u043e\u043b\u043e\u0442\u043e\u0432\u0430 \u0413.\u0410. \u0440\u0430\u0437\u043b\u0438\u0447\u0430\u0435\u0442 \u0442\u0440\u0438 \u0442\u0430\u043a\u0438\u0445 \u0444\u0443\u043d\u043a\u0446\u0438\u043e\u043d\u0430\u043b\u044c\u043d\u044b\u0445 \u0440\u043e\u043b\u0438:\n1) \u0432\u043e\u0437\u043c\u043e\u0436\u043d\u043e\u0441\u0442\u044c \u0441\u0430\u043c\u043e\u0441\u0442\u043e\u044f\u0442\u0435\u043b\u044c\u043d\u043e\u0433\u043e \u043d\u0435\u0437\u0430\u0432\u0438\u0441\u0438\u043c\u043e\u0433\u043e \u0441\u0443\u0449\u0435\u0441\u0442\u0432\u043e\u0432\u0430\u043d\u0438\u044f \u0441\u0438\u043d\u0442\u0430\u043a\u0441\u0435\u043c\u044b;\n2) \u0438\u0441\u043f\u043e\u043b\u044c\u0437\u043e\u0432\u0430\u043d\u0438\u0435 \u0441\u0438\u043d\u0442\u0430\u043a\u0441\u0435\u043c\u044b \u0432 \u043a\u0430\u0447\u0435\u0441\u0442\u0432\u0435 \u043a\u043e\u043c\u043f\u043e\u043d\u0435\u043d\u0442\u0430 \u043f\u0440\u0435\u0434\u043b\u043e\u0436\u0435\u043d\u0438\u044f;\n3) \u0438\u0441\u043f\u043e\u043b\u044c\u0437\u043e\u0432\u0430\u043d\u0438\u0435 \u0441\u0438\u043d\u0442\u0430\u043a\u0441\u0435\u043c\u044b \u0432 \u043a\u0430\u0447\u0435\u0441\u0442\u0432\u0435 \u043a\u043e\u043c\u043f\u043e\u043d\u0435\u043d\u0442\u0430 \u0441\u043b\u043e\u0432\u043e\u0441\u043e\u0447\u0435\u0442\u0430\u043d\u0438\u044f (\u0438\u043b\u0438 \u0441\u043e\u0447\u0435\u0442\u0430\u043d\u0438\u044f \u0441\u043b\u043e\u0432), \u0442\u0430\u043a \u043d\u0430\u0437\u044b\u0432\u0430\u0435\u043c\u043e\u0435 \u043f\u0440\u0438\u0441\u043b\u043e\u0432\u043d\u043e\u0435 \u0443\u043f\u043e\u0442\u0440\u0435\u0431\u043b\u0435\u043d\u0438\u0435.\n\u0424\u0443\u043d\u043a\u0446\u0438\u043e\u043d\u0430\u043b\u044c\u043d\u044b\u0435 \u0441\u0432\u043e\u0439\u0441\u0442\u0432\u0430 \u0441\u0438\u043d\u0442\u0430\u043a\u0441\u0435\u043c \u0441\u043b\u0443\u0436\u0430\u0442 \u043e\u0441\u043d\u043e\u0432\u043e\u0439 \u0434\u043b\u044f \u0440\u0430\u0437\u0433\u0440\u0430\u043d\u0438\u0447\u0435\u043d\u0438\u044f \u0442\u0440\u0435\u0445 \u0438\u0445 \u0432\u043e\u0437\u043c\u043e\u0436\u043d\u044b\u0445 \u0442\u0438\u043f\u043e\u0432, \u043d\u0430\u0437\u044b\u0432\u0430\u0435\u043c\u044b\u0445 \u0441\u043e\u043e\u0442\u0432\u0435\u0442\u0441\u0442\u0432\u0435\u043d\u043d\u043e, \u0441\u0432\u043e\u0431\u043e\u0434\u043d\u044b\u043c\u0438 \u2013 \u0410 (\u0438\u043b\u0438 \u043e\u0431\u043b\u0430\u0434\u0430\u044e\u0449\u0438\u043c\u0438 \u043f\u043e\u043b\u043d\u044b\u043c \u0444\u0443\u043d\u043a\u0446\u0438\u043e\u043d\u0430\u043b\u044c\u043d\u044b\u043c \u0440\u0435\u043f\u0435\u0440\u0442\u0443\u0430\u0440\u043e\u043c), \u043e\u0431\u0443\u0441\u043b\u043e\u0432\u043b\u0435\u043d\u043d\u044b\u043c\u0438 \u2013 \u0411 (\u0441\u043f\u043e\u0441\u043e\u0431\u043d\u044b\u043c\u0438\n\u0432\u044b\u043f\u043e\u043b\u043d\u044f\u0442\u044c \u0444\u0443\u043d\u043a\u0446\u0438\u0438 2, 3, \u043a\u0440\u0430\u0439\u043d\u0435 \u0438\u0437\u0440\u0435\u0434\u043a\u0430 1), \u0441\u0432\u044f\u0437\u0430\u043d\u043d\u044b\u043c\u0438 \u2013 \u0412 (\u0432\u044b\u0441\u0442\u0443\u043f\u0430\u044e\u0449\u0438\u043c\u0438 \u0442\u043e\u043b\u044c\u043a\u043e \u0432 \u0440\u043e\u043b\u0438 3). \u041e\u0447\u0435\u0432\u0438\u0434\u043d\u043e, \u0447\u0442\u043e \u0444\u0443\u043d\u043a\u0446\u0438\u043e\u043d\u0430\u043b\u044c\u043d\u044b\u0435 \u0441\u0432\u043e\u0439\u0441\u0442\u0432\u0430 \u0441\u0438\u043d\u0442\u0430\u043a\u0441\u0435\u043c \u0438\u043c\u0435\u044e\u0442 \u0442\u0440\u0430\u043d\u0437\u0438\u0442\u0438\u0432\u043d\u044b\u0439 \u0445\u0430\u0440\u0430\u043a\u0442\u0435\u0440.\n\u0420\u0430\u0441\u0441\u043c\u0430\u0442\u0440\u0438\u0432\u0430\u044f \u0442\u0435\u043a\u0441\u0442 \u043a\u0430\u043a \u0434\u0438\u043d\u0430\u043c\u0438\u0447\u0435\u0441\u043a\u0443\u044e \u0441\u0438\u0441\u0442\u0435\u043c\u0443, \u043c\u044b \u0438\u043c\u0435\u0435\u043c \u0432\u043e\u0437\u043c\u043e\u0436\u043d\u043e\u0441\u0442\u044c \u043e\u043f\u0438\u0441\u0430\u0442\u044c \u0432\u0435\u0441\u044c \u043f\u0440\u043e\u0446\u0435\u0441\u0441 \u043f\u043e\u0441\u0442\u0440\u043e\u0435\u043d\u0438\u044f \u043e\u043d\u0442\u043e\u043b\u043e\u0433\u0438\u0438 \u043a\u0430\u043a \u0446\u0435\u043b\u0435\u043d\u0430\u043f\u0440\u0430\u0432\u043b\u0435\u043d\u043d\u0443\u044e \u043e\u043f\u0435\u0440\u0430\u0446\u0438\u043e\u043d\u043d\u0443\u044e \u0434\u0435\u044f\u0442\u0435\u043b\u044c\u043d\u043e\u0441\u0442\u044c \u0432 \u043f\u0440\u0435\u0434\u0435\u043b\u0430\u0445 \u0434\u0430\u043d\u043d\u043e\u0439 \u0441\u0438\u0441\u0442\u0435\u043c\u044b, \u043e\u0440\u0433\u0430\u043d\u0438\u0437\u043e\u0432\u0430\u043d\u043d\u0443\u044e \u0434\u043b\u044f \u0440\u0435\u0448\u0435\u043d\u0438\u044f \u0437\u0430\u0434\u0430\u0447 \u0441\u043e\u0434\u0435\u0440\u0436\u0430\u0442\u0435\u043b\u044c\u043d\u043e\u0433\u043e \u043d\u0430\u043f\u043e\u043b\u043d\u0435\u043d\u0438\u044f \u044d\u043b\u0435\u043c\u0435\u043d\u0442\u043e\u0432 \u043e\u043d\u0442\u043e\u043b\u043e\u0433\u0438\u0438. \u041c\u0430\u0442\u0435\u043c\u0430\u0442\u0438\u0447\u0435\u0441\u043a\u0438 \u043e\u043d\u0442\u043e\u043b\u043e\u0433\u0438\u044f \u043e\u043f\u0440\u0435\u0434\u0435\u043b\u044f\u0435\u0442\u0441\u044f \u0441\u043b\u0435\u0434\u0443\u044e\u0449\u0438\u043c \u043e\u0431\u0440\u0430\u0437\u043e\u043c [6]:\n), ,T\u03c3\u0391,,\u03c3R,c,(C,\u039f: \u0391RR  , \u0433\u0434\u0435:\n1. C, R, A,T \u2013 \u044f\u0432\u043b\u044f\u044e\u0442\u0441\u044f \u043d\u0435\u0441\u0432\u044f\u0437\u0430\u043d\u043d\u044b\u043c\u0438 \u043c\u043d\u043e\u0436\u0435\u0441\u0442\u0432\u0430\u043c\u0438, \u0447\u044c\u0438 \u044d\u043b\u0435\u043c\u0435\u043d\u0442\u044b \u043d\u0430\u0437\u044b\u0432\u0430\u044e\u0442\u0441\u044f\n\u0438\u0434\u0435\u043d\u0442\u0438\u0444\u0438\u043a\u0430\u0442\u043e\u0440\u0430\u043c\u0438 \u043a\u043e\u043d\u0446\u0435\u043f\u0442\u043e\u0432, \u043e\u0442\u043d\u043e\u0448\u0435\u043d\u0438\u0439, \u0430\u0442\u0440\u0438\u0431\u0443\u0442\u043e\u0432 \u0438 \u0442\u0438\u043f\u043e\u0432 \u0434\u0430\u043d\u043d\u044b\u0445 \u0441\u043e\u043e\u0442\u0432\u0435\u0442\u0441\u0442\u0432\u0435\u043d\u043d\u043e; 2. \u2264c \u2013 \u043f\u043e\u043b\u0443\u0441\u0432\u044f\u0437\u0430\u043d\u043d\u0430\u044f \u0442\u0430\u043a\u0441\u043e\u043d\u043e\u043c\u0438\u044f (semi-upper lattice) \u043a\u043e\u043d\u0446\u0435\u043f\u0442\u043e\u0432 \u0441 \u043e\u0431\u0449\u0438\u043c \u044d\u043b\u0435\u043c\u0435\u043d\u0442\u043e\u043c\n\u0441\u0430\u043c\u043e\u0433\u043e \u0432\u0435\u0440\u0445\u043d\u0435\u0433\u043e \u0443\u0440\u043e\u0432\u043d\u044f rootC;\n3. \u0444\u0443\u043d\u043a\u0446\u0438\u044f \u03c3R:RC+ \u043d\u0430\u0437\u044b\u0432\u0430\u0435\u043c\u0430\u044f \u043f\u0440\u0438\u0437\u043d\u0430\u043a\u043e\u043c \u043e\u0442\u043d\u043e\u0448\u0435\u043d\u0438\u044f (relation signature); 4. \u2264R on R, \u0438\u0435\u0440\u0430\u0440\u0445\u0438\u044f \u043e\u0442\u043d\u043e\u0448\u0435\u043d\u0438\u0439 \u0433\u0434\u0435, r1 \u2264R r2 \u043f\u043e\u0434\u0440\u0430\u0437\u0443\u043c\u0435\u0432\u0430\u0435\u0442 =|\u03c3R(r1)| =|\u03c3R(r2)| \u0438\ni(\u03c3R(r1)) \u2264c i(\u03c3R(r2)) \u0434\u043b\u044f \u043a\u0430\u0436\u0434\u043e\u0433\u043e \u2264 i \u2264 =|\u03c3R(r1)|;\n5. \u0444\u0443\u043d\u043a\u0446\u0438\u044f \u03c3A:AC\u00d7T \u043d\u0430\u0437\u044b\u0432\u0430\u0435\u043c\u0430\u044f \u043f\u0440\u0438\u0437\u043d\u0430\u043a\u043e\u043c \u0430\u0442\u0440\u0438\u0431\u0443\u0442\u0430 (attribute signature); 6. \u043c\u043d\u043e\u0436\u0435\u0441\u0442\u0432\u043e \u0442\u0438\u043f\u043e\u0432 \u0434\u0430\u043d\u043d\u044b\u0445 (datatypes) T, \u0442\u0430\u043a\u0438\u0445 \u043a\u0430\u043a \u0441\u0442\u0440\u043e\u043a\u0438, \u0446\u0435\u043b\u044b\u0435 \u0447\u0438\u0441\u043b\u0430 \u0438 \u0442.\u0434.\n\u0414\u043b\u044f \u043e\u0431\u0435\u0441\u043f\u0435\u0447\u0435\u043d\u0438\u044f \u044f\u0437\u044b\u043a\u043e\u0432\u043e\u0439 \u043a\u043e\u043c\u043f\u0435\u0442\u0435\u043d\u0442\u043d\u043e\u0441\u0442\u0438,\n\u0434\u043e\u0441\u0442\u0430\u0442\u043e\u0447\u043d\u043e\u0439 \u0434\u043b\u044f \u043f\u043e\u0441\u0442\u0440\u043e\u0435\u043d\u0438\u044f \u0438 \u0441\u0430\u043c\u043e\u043e\u0431\u0443\u0447\u0435\u043d\u0438\u044f \u043e\u043d\u0442\u043e\u043b\u043e\u0433\u0438\u0438 \u043f\u0440\u0435\u0434\u043c\u0435\u0442\u043d\u043e\u0439 \u043e\u0431\u043b\u0430\u0441\u0442\u0438 \u043d\u0430 \u0431\u0430\u0437\u0435 \u0442\u0435\u043a\u0441\u0442\u0430, \u0418\u0421 \u0441\u0430\u043c\u0430 \u0434\u043e\u043b\u0436\u043d\u0430 \u043e\u0431\u043b\u0430\u0434\u0430\u0442\u044c \u0437\u043d\u0430\u043d\u0438\u044f\u043c\u0438 \u0441\u043e\u043e\u0442\u0432\u0435\u0442\u0441\u0442\u0432\u0443\u044e\u0449\u0435\u0433\u043e \u043f\u043e\u0440\u044f\u0434\u043a\u0430, \u043e\u0431\u0449\u0438\u043c\u0438 (\u044f\u0437\u044b\u043a\u043e\u0432\u044b\u043c\u0438) \u0438 \u0441\u043f\u0435\u0446\u0438\u0430\u043b\u044c\u043d\u044b\u043c\u0438, (\u043e\u0442\u043d\u043e\u0441\u044f\u0449\u0438\u043c\u0438\u0441\u044f \u043a \u0434\u0430\u043d\u043d\u043e\u0439 \u041f\u041e). \u0422\u0430\u043a\u0430\u044f \u0418\u0421 \u0434\u043e\u043b\u0436\u043d\u0430, \u043f\u043e \u0441\u0443\u0442\u0438, \u043e\u0431\u044a\u0435\u0434\u0438\u043d\u044f\u0442\u044c \u0432 \u0441\u0435\u0431\u0435 \u0434\u0432\u0435 \u00ab\u0432\u0441\u0442\u0440\u043e\u0435\u043d\u043d\u044b\u0435\u00bb \u043e\u043d\u0442\u043e\u043b\u043e\u0433\u0438\u0438: \u043e\u043d\u0442\u043e\u043b\u043e\u0433\u0438\u044e \u044f\u0437\u044b\u043a\u0430 (\u0440\u0443\u0441\u0441\u043a\u043e\u0433\u043e) \u0438 \u0431\u0430\u0437\u043e\u0432\u0443\u044e (\u0441\u0442\u0430\u0440\u0442\u043e\u0432\u0443\u044e) \u043e\u043d\u0442\u043e\u043b\u043e\u0433\u0438\u044e \u041f\u041e. \u041c\u043d\u043e\u0433\u043e\u0447\u0438\u0441\u043b\u0435\u043d\u043d\u044b\u0435 \u044d\u043b\u0435\u043a\u0442\u0440\u043e\u043d\u043d\u044b\u0435 \u0441\u043b\u043e\u0432\u0430\u0440\u0438-\u0442\u0435\u0437\u0430\u0443\u0440\u0443\u0441\u044b (MRD \u2013 machine readable dictionary), \u0441 \u043b\u0435\u043a\u0441\u0438\u043a\u043e\u0433\u0440\u0430\u0444\u0438\u0447\u0435\u0441\u043a\u043e\u0439 \u0440\u0430\u0437\u043c\u0435\u0442\u043a\u043e\u0439 (\u043a\u0430\u043a\u0438\u0435 \u043a\u0430\u043a WordNet \u0438 \u0435\u0433\u043e \u0440\u0443\u0441\u0441\u043a\u043e\u044f\u0437\u044b\u0447\u043d\u044b\u0435 \u0430\u043d\u0430\u043b\u043e\u0433\u0438 RussNet, RuNet \u0438 \u0434\u0440.) \u043c\u043e\u0436\u043d\u043e \u0440\u0430\u0441\u0441\u043c\u0430\u0442\u0440\u0438\u0432\u0430\u0442\u044c \u043a\u0430\u043a \u044d\u043b\u0435\u043c\u0435\u043d\u0442\u044b \u0421 \u0438 \u2264c \u0442\u0440\u0435\u0431\u0443\u0435\u043c\u043e\u0439 \u043b\u0438\u043d\u0433\u0432\u0438\u0441\u0442\u0438\u0447\u0435\u0441\u043a\u043e\u0439 \u043e\u043d\u0442\u043e\u043b\u043e\u0433\u0438\u0438. \u041f\u0430\u0440\u0441\u0435\u0440\u044b \u044f\u0437\u044b\u043a\u0430 (\u043d\u0430\u043f\u0440\u0438\u043c\u0435\u0440, \u043f\u0440\u043e\u0435\u043a\u0442 \u0410\u041e\u0422 [6]) \u043c\u043e\u0433\u0443\u0442 \u0431\u044b\u0442\u044c \u0443\u0441\u043f\u0435\u0448\u043d\u043e \u0438\u0441\u043f\u043e\u043b\u044c\u0437\u043e\u0432\u0430\u043d\u044b \u043a\u0430\u043a \u0434\u043b\u044f \u043e\u043f\u0440\u0435\u0434\u0435\u043b\u0435\u043d\u0438\u044f \u0440\u043e\u043b\u0435\u0439 \u043a\u043e\u043d\u0446\u0435\u043f\u0442\u043e\u0432, \u0442\u0430\u043a \u0438 \u0434\u043b\u044f \u043e\u043f\u0440\u0435\u0434\u0435\u043b\u0435\u043d\u0438\u044f \u0438\u0445 \u0430\u0442\u0440\u0438\u0431\u0443\u0442\u043e\u0432. \u0422\u043e, \u0447\u0435\u0433\u043e \u0434\u0435\u0439\u0441\u0442\u0432\u0438\u0442\u0435\u043b\u044c\u043d\u043e \u043d\u0435 \u0445\u0432\u0430\u0442\u0430\u0435\u0442 \u0434\u043b\u044f \u043f\u043e\u043b\u043d\u043e\u0446\u0435\u043d\u043d\u043e\u0439 \u0438\u043d\u0442\u0435\u043b\u043b\u0435\u043a\u0442\u0443\u0430\u043b\u044c\u043d\u043e\u0439 \u0441\u0438\u0441\u0442\u0435\u043c\u044b, \u0442\u0430\u043a \u044d\u0442\u043e \u0441\u0438\u0441\u0442\u0435\u043c\u0430\u0442\u0438\u0437\u0438\u0440\u043e\u0432\u0430\u043d\u043d\u043e\u0433\u043e \u0440\u0435\u043f\u0435\u0440\u0442\u0443\u0430\u0440\u0430 \u043b\u0435\u043a\u0441\u0438\u043a\u043e-\u0441\u0438\u043d\u0442\u0430\u043a\u0441\u0438\u0447\u0435\u0441\u043a\u0438\u0445 \u0435\u0434\u0438\u043d\u0438\u0446 \u044f\u0437\u044b\u043a\u0430, \u043d\u0435\u0441\u0443\u0449\u0438\u0445 \u0432 \u0441\u0435\u0431\u0435 \u043e\u0434\u043d\u043e\u0437\u043d\u0430\u0447\u043d\u043e \u0442\u0440\u0430\u043a\u0442\u0443\u0435\u043c\u0443\u044e \u0441\u0435\u043c\u0430\u043d\u0442\u0438\u043a\u0443 \u0438 \u043e\u0434\u043d\u043e\u0432\u0440\u0435\u043c\u0435\u043d\u043d\u043e \u0432\u044b\u043f\u043e\u043b\u043d\u044f\u044e\u0449\u0438\u0445 \u0440\u043e\u043b\u044c \u00ab\u044d\u043b\u0435\u043c\u0435\u043d\u0442\u0430\u0440\u043d\u044b\u0445 \u0435\u0434\u0438\u043d\u0438\u0446 \u0441\u0431\u043e\u0440\u043a\u0438\u00bb \u0432\u044b\u0441\u043a\u0430\u0437\u044b\u0432\u0430\u043d\u0438\u0439 (\u0442\u0435\u043a\u0441\u0442\u043e\u0432). \u041f\u0435\u0440\u0435\u0441\u0435\u0447\u0435\u043d\u0438\u0435 \u0442\u0430\u043a\u043e\u0433\u043e \u0440\u0435\u043f\u0435\u0440\u0442\u0443\u0430\u0440\u0430 \u00ab\u0430\u0440\u0445\u0435-\u0444\u0443\u043d\u043a\u0446\u0438\u0439\u00bb, \u043d\u0435\u0441\u043e\u043c\u044b\u0445 \u0441\u0438\u043d\u0442\u0430\u043a\u0441\u0438\u0447\u0435\u0441\u043a\u043e\u0439 \u0444\u043e\u0440\u043c\u043e\u0439 \u0438 \u0440\u0435\u043f\u0435\u0440\u0442\u0443\u0430\u0440\u0430 \u0441\u043b\u043e\u0432\u043d\u043e\u0441\u0438\u0442\u0435\u043b\u0435\u0439 \u043a\u0430\u0442\u0435\u0433\u043e\u0440\u0438\u0430\u043b\u044c\u043d\u044b\u0445 \u0440\u0435\u0444\u0435\u0440\u0435\u043d\u0446\u0438\u0439, \u0434\u0430\u0435\u0442 \u043f\u0440\u043e\u0435\u043a\u0446\u0438\u044e \u043e\u0434\u043d\u043e\u0437\u043d\u0430\u0447\u043d\u043e \u0442\u0440\u0430\u043a\u0442\u0443\u0435\u043c\u043e\u0439 \u0440\u043e\u043b\u0438 (\u0444\u0443\u043d\u043a\u0446\u0438\u0438) \u0432\u044b\u043f\u043e\u043b\u043d\u044f\u0435\u043c\u043e\u0439 \u0434\u0430\u043d\u043d\u044b\u043c \u043f\u043e\u043d\u044f\u0442\u0438\u0435\u043c. \u041f\u043e\u0434\u043e\u0431\u043d\u044b\u0439 \u0441\u0438\u0441\u0442\u0435\u043c\u0430\u0442\u0438\u0437\u0438\u0440\u0443\u044e\u0449\u0438\u0439 \u0442\u0440\u0443\u0434, \u043a\u0430\u043a \u0431\u044b\u043b\u043e \u0441\u043a\u0430\u0437\u0430\u043d\u043e \u0432\u044b\u0448\u0435, \u0432\u044b\u043f\u043e\u043b\u043d\u0435\u043d \u0432 \u0437\u043d\u0430\u0447\u0438\u0442\u0435\u043b\u044c\u043d\u043e\u0439 \u0441\u0442\u0435\u043f\u0435\u043d\u0438 \u0417\u043e\u043b\u043e\u0442\u043e\u0432\u043e\u0439 \u0413.\u0410. [8] \u0438 \u0436\u0434\u0435\u0442 \u0434\u043e\u0441\u0442\u043e\u0439\u043d\u043e\u0439 \u0442\u0435\u0445\u043d\u0438\u0447\u0435\u0441\u043a\u043e\u0439 \u0440\u0435\u0430\u043b\u0438\u0437\u0430\u0446\u0438\u0438.\n\u0418\u0421 \u0434\u043b\u044f \u0430\u0432\u0442\u043e\u043c\u0430\u0442\u0438\u0437\u0438\u0440\u043e\u0432\u0430\u043d\u043d\u043e\u0433\u043e\n\u043e\u0431\u043d\u0430\u0440\u0443\u0436\u0435\u043d\u0438\u044f \u043a\u043e\u043d\u0446\u0435\u043f\u0442\u043e\u0432 \u043e\u043d\u0442\u043e\u043b\u043e\u0433\u0438\u0438 \u041f\u041e\n\u041f\u0440\u0435\u0434\u043b\u0430\u0433\u0430\u0435\u043c\u044b\u0439 \u043f\u043e\u0434\u0445\u043e\u0434 \u0430\u0432\u0442\u043e\u043c\u0430\u0442\u0438\u0437\u0438\u0440\u043e\u0432\u0430\u043d\u043d\u043e\u0433\u043e \u043f\u043e\u0441\u0442\u0440\u043e\u0435\u043d\u0438\u044f \u043e\u043d\u0442\u043e\u043b\u043e\u0433\u0438\u0438 \u041f\u041e, \u0441\u043e\u0447\u0435\u0442\u0430\u0435\u0442 \u0432 \u0441\u0435\u0431\u0435 \u0431\u044b\u0441\u0442\u0440\u043e\u0442\u0443 \u0441\u0442\u0430\u0442\u0438\u0441\u0442\u0438\u0447\u0435\u0441\u043a\u0438\u0445 \u043c\u0435\u0442\u043e\u0434\u043e\u0432 \u0438 \u0442\u043e\u0447\u043d\u043e\u0441\u0442\u044c\n\u043b\u0438\u043d\u0433\u0432\u0438\u0441\u0442\u0438\u0447\u0435\u0441\u043a\u043e\u0433\u043e \u043f\u043e\u0434\u0445\u043e\u0434\u0430 \u0441 \u043f\u043e\u0437\u0438\u0446\u0438\u0439 \u0441\u0438\u043d\u0442\u0430\u043a\u0441\u0435\u043c (\u0438\u043b\u0438 \u043b\u0438\u043d\u0433\u0432\u0438\u0441\u0442\u0438\u0447\u0435\u0441\u043a\u0438\u0445 \u0448\u0430\u0431\u043b\u043e\u043d\u043e\u0432).\n\u041f\u0440\u043e\u0446\u0435\u0441\u0441 \u043f\u043e\u0441\u0442\u0440\u043e\u0435\u043d\u0438\u044f \u043e\u043d\u0442\u043e\u043b\u0433\u0438\u0438 \u0441\u043e\u0441\u0442\u043e\u0438\u0442 \u0438\u0437\n\u043d\u0435\u0441\u043a\u043e\u043b\u044c\u043a\u0438\u0445 \u043f\u043e\u0441\u043b\u0435\u0434\u043e\u0432\u0430\u0442\u0435\u043b\u044c\u043d\u044b\u0445 \u044d\u0442\u0430\u043f\u043e\u0432:\n1. \u0420\u0430\u0437\u043c\u0435\u0442\u043a\u0430 \u043a\u043e\u0440\u043f\u0443\u0441\u0430 \u0441\u0438\u043d\u0442\u0430\u043a\u0441\u0438\u0447\u0435\u0441\u043a\u0438\u043c\u0438 \u0442\u0435\u0433\u0430\u043c\u0438 (\u043d\u0430\u043f\u0440\u043c\u0435\u0440, \u0438\u043d\u0444\u043e\u0440\u043c\u0430\u0446\u0438\u0435\u0439 \u043e \u0447\u0430\u0441\u0442\u0438 \u0440\u0435\u0447\u0438, \u0440\u043e\u0434\u0435\n\u0447\u0438\u0441\u043b\u0435 \u0438 \u0442.\u0434.).\n2. \u041e\u043f\u0440\u0435\u0434\u0435\u043b\u0435\u043d\u0438\u0435 \u0445\u0430\u0440\u0430\u043a\u0442\u0435\u0440\u043d\u044b\u0445, \u0442.\u0435. \u043d\u0430\u0438\u0431\u043e\u043b\u0435\u0435 \u0447\u0430\u0441\u0442\u043e \u0432\u0441\u0442\u0440\u0435\u0447\u0430\u044e\u0449\u0438\u0445\u0441\u044f \u0432 \u043a\u043e\u0440\u043f\u0443\u0441\u0435\n\u043b\u0438\u043d\u0433\u0432\u0438\u0441\u0442\u0438\u0447\u0435\u0441\u043a\u0438\u0445 \u0441\u0442\u0440\u0443\u043a\u0442\u0443\u0440 \u0438 \u0444\u043e\u0440\u043c\u0438\u0440\u043e\u0432\u0430\u043d\u0438\u0435 \u043d\u0430 \u0438\u0445 \u043e\u0441\u043d\u043e\u0432\u0435 \u043b\u0438\u0433\u0432\u0438\u0441\u0442\u0438\u0447\u0435\u0441\u043a\u0438\u0445 \u0448\u0430\u0431\u043b\u043e\u043d\u043e\u0432. 3. \u041f\u043e\u0438\u0441\u043a \u0444\u0440\u0430\u0433\u043c\u0435\u043d\u0442\u043e\u0432 \u0442\u0435\u043a\u0441\u0442\u0430, \u0441\u043e\u043e\u0442\u0432\u0435\u0442\u0432\u0443\u044e\u0449\u0438\u0445 \u0434\u0430\u043d\u043d\u044b\u043c \u0448\u0430\u0431\u043b\u043e\u043d\u0430\u043c. 4. \u041d\u043e\u0440\u043c\u0430\u043b\u0438\u0437\u0430\u0446\u0438\u044f \u0438 \u0434\u043e\u0431\u0430\u0432\u043b\u0435\u043d\u0438\u0435 \u0432 \u0431\u0430\u0437\u043e\u0432\u0443\u044e \u043e\u043d\u0442\u043e\u043b\u043e\u0433\u0438\u044e \u043d\u043e\u0432\u044b\u0445 \u043a\u043e\u043d\u0446\u0435\u043f\u0442\u043e\u0432, \u0432\u044b\u044f\u0432\u043b\u0435\u043d\u043d\u044b\u0445\n\u043d\u0430 \u043f\u0440\u0435\u0434\u044b\u0434\u0443\u0449\u0435\u043c \u044d\u0442\u0430\u043f\u0435.\n\u041d\u0430 \u0442\u0440\u0435\u0442\u044c\u0435\u043c \u044d\u0442\u0430\u043f\u0435 \u043d\u0435\u043e\u0431\u0445\u043e\u0434\u0438\u043c\u043e \u043f\u0440\u0438\u0432\u043b\u0435\u0447\u0435\u043d\u0438\u0435 \u044d\u043a\u0441\u043f\u0435\u0440\u0442\u0430 \u043f\u0440\u0435\u0434\u043c\u0435\u0442\u043d\u043e\u0439 \u043e\u0431\u043b\u0430\u0441\u0442\u0438 \u0434\u043b\u044f \u043e\u0446\u0435\u043d\u043a\u0438 \u0440\u0435\u043b\u0435\u0432\u0430\u043d\u0442\u043d\u043e\u0441\u0442\u0438 \u043d\u0430\u0439\u0434\u0435\u043d\u043d\u044b\u0445 \u043f\u043e\u0442\u0435\u043d\u0446\u0438\u0430\u043b\u044c\u043d\u044b\u0445 \u043a\u043e\u043d\u0446\u0435\u043f\u0442\u043e\u0432.\n\u041f\u0440\u043e\u0438\u043b\u043b\u044e\u0441\u0442\u0438\u0440\u0443\u0435\u043c \u0441\u043a\u0430\u0437\u0430\u043d\u043d\u043e\u0435 \u043f\u0440\u0438\u043c\u0435\u0440\u043e\u043c\n\u0430\u043d\u0430\u043b\u0438\u0437\u0430 \u0441\u043b\u0435\u0434\u0443\u044e\u0449\u0435\u0433\u043e \u0442\u0435\u043a\u0441\u0442\u0430 (\u0444\u0440\u0430\u0433\u043c\u0435\u043d\u0442 \u0440\u0435\u043a\u043e\u043c\u0435\u043d\u0434\u0430\u0446\u0438\u0438 \u041c\u0410\u0413\u0410\u0422\u042d 2000 \u0433.):\n\u00ab\u041f\u043e\u0441\u043b\u0435 \u0430\u0432\u0430\u0440\u0438\u0439\u043d\u043e\u0433\u043e \u043e\u0431\u043b\u0443\u0447\u0435\u043d\u0438\u044f \u0431\u043e\u043b\u044c\u0448\u043e\u0439\n\u043c\u043e\u0449\u043d\u043e\u0441\u0442\u0438 \u0440\u0430\u0437\u0432\u0438\u0442\u0438\u0435 \u043f\u043e\u0440\u0430\u0436\u0435\u043d\u0438\u0439 \u043f\u043e \u0432\u0440\u0435\u043c\u0435\u043d\u0438 \u043f\u0440\u043e\u0445\u043e\u0434\u0438\u0442 \u0447\u0435\u0440\u0435\u0437 \u0447\u0435\u0442\u043a\u043e \u043e\u043f\u0440\u0435\u0434\u0435\u043b\u0435\u043d\u043d\u044b\u0435 \u0441\u0442\u0430\u0434\u0438\u0438. \u041f\u0440\u043e\u0434\u043e\u043b\u0436\u0438\u0442\u0435\u043b\u044c\u043d\u043e\u0441\u0442\u044c \u0438 \u0432\u0440\u0435\u043c\u044f \u043d\u0430\u0441\u0442\u0443\u043f\u043b\u0435\u043d\u0438\u044f \u0441\u0442\u0430\u0434\u0438\u0439 \u0437\u0430\u0432\u0438\u0441\u0438\u0442 \u043e\u0442 \u0434\u043e\u0437\u044b. \u041c\u0430\u043b\u044b\u0435 \u0434\u043e\u0437\u044b \u043d\u0435 \u0434\u0430\u044e\u0442 \u043d\u0430\u0431\u043b\u044e\u0434\u0430\u0435\u043c\u044b\u0445 \u044d\u0444\u0444\u0435\u043a\u0442\u043e\u0432. \u0422\u0438\u043f\u0438\u0447\u043d\u043e\u0435 \u0440\u0430\u0437\u0432\u0438\u0442\u0438\u0435 \u0441\u043e\u0431\u044b\u0442\u0438\u0439 \u043f\u043e\u0441\u043b\u0435 \u043e\u0431\u043b\u0443\u0447\u0435\u043d\u0438\u044f \u0432\u0441\u0435\u0433\u043e \u0442\u0435\u043b\u0430 \u043e\u0442 \u0438\u0441\u0442\u043e\u0447\u043d\u0438\u043a\u0430 \u043f\u0440\u043e\u043d\u0438\u043a\u0430\u044e\u0449\u0435\u0439 \u0440\u0430\u0434\u0438\u0430\u0446\u0438\u0438 \u0432\u043a\u043b\u044e\u0447\u0430\u0435\u0442 \u043d\u0430\u0447\u0430\u043b\u044c\u043d\u0443\u044e \u043f\u0440\u043e\u0434\u0440\u043e\u043c\u0430\u043b\u044c\u043d\u0443\u044e \u0441\u0442\u0430\u0434\u0438\u044e \u0441 \u0442\u0430\u043a\u0438\u043c\u0438 \u0441\u0438\u043c\u043f\u0442\u043e\u043c\u0430\u043c\u0438, \u043a\u0430\u043a \u0442\u043e\u0448\u043d\u043e\u0442\u0430, \u0440\u0432\u043e\u0442\u0430, \u0443\u0441\u0442\u0430\u043b\u043e\u0441\u0442\u044c \u0438, \u0432\u043e\u0437\u043c\u043e\u0436\u043d\u043e, \u043b\u0438\u0445\u043e\u0440\u0430\u0434\u043a\u0430 \u0438 \u0434\u0438\u0430\u0440\u0435\u044f, \u043f\u043e\u0441\u043b\u0435 \u0447\u0435\u0433\u043e \u0441\u043b\u0435\u0434\u0443\u0435\u0442 \u043b\u0430\u0442\u0435\u043d\u0442\u043d\u044b\u0439 \u043f\u0435\u0440\u0438\u043e\u0434 \u0440\u0430\u0437\u043b\u0438\u0447\u043d\u043e\u0439 \u043f\u0440\u043e\u0434\u043e\u043b\u0436\u0438\u0442\u0435\u043b\u044c\u043d\u043e\u0441\u0442\u0438.\u00bb\n\u041c\u043e\u0434\u0443\u043b\u044c \u043b\u0438\u043d\u0433\u0432\u0438\u0441\u0442\u0438\u0447\u0435\u0441\u043a\u043e\u0439 \u043e\u043d\u0442\u043e\u043b\u043e\u0433\u0438\u0438 \u0418\u0421\n\u0440\u0430\u0441\u043f\u043e\u0437\u043d\u0430\u0435\u0442 \u0442\u0430\u043a\u0438\u0435 \u0441\u0432\u043e\u0439\u0441\u0442\u0432\u0430 \u043a\u043e\u043d\u0446\u0435\u043f\u0442\u043e\u0432: \u043a\u0432\u0430\u043b\u0438\u0442\u0430\u0442\u0438\u0432\n(\u043a\u0430\u0447\u0435\u0441\u0442\u0432\u043e) \u0441\u0443\u0431\u044a\u0435\u043a\u0442\u0430 \u0438 \u0435\u0433\u043e \u043e\u0431\u044a\u0435\u043a\u0442. \u0412 \u0440\u0443\u0441\u0441\u043a\u043e\u043c \u044f\u0437\u044b\u043a\u0435 \u044d\u0442\u043e \u043c\u043e\u0436\u0435\u0442 \u0432\u044b\u0440\u0430\u0436\u0430\u0442\u044c\u0441\u044f \u0441\u043b\u0435\u0434\u0443\u044e\u0449\u0438\u043c\u0438 \u0444\u043e\u0440\u043c\u0443\u043b\u0430\u043c\u0438:\n1. \u0432\u0441\u043f\u043e\u043c\u043e\u0433\u0430\u0442\u0435\u043b\u044c\u043d\u044b\u043c\u0438 \u0433\u043b\u0430\u0433\u043e\u043b\u0430\u043c\u0438 {\u043e\u0442\u043b\u0438\u0447\u0430\u0442\u044c\u0441\u044f, \u0432\u044b\u0440\u0430\u0436\u0430\u0442\u044c\u0441\u044f, \u043f\u0440\u043e\u044f\u0432\u043b\u044f\u0442\u044c\u0441\u044f, \u0445\u0430\u0440\u0430\u043a\u0442\u0435\u0440\u0438\u0437\u043e\u0432\u0430\u0442\u044c\u0441\u044f,\n\u043e\u0431\u043b\u0430\u0434\u0430\u0442\u044c} + \u0422.\u043f. \u043f\u0440\u0438\u0437\u043d\u0430\u043a\u043e\u0432\u043e\u0433\u043e \u0441\u043b\u043e\u0432\u0430 (\u043f\u0440\u0435\u0434\u0438\u0446\u0438\u0440\u0443\u044e\u0449\u0438\u0439 \u043a\u043e\u043c\u043f\u043e\u043d\u0435\u043d\u0442); 2. c \u043f\u043e\u043c\u043e\u0449\u044c\u044e \u0440\u043e\u0434\u0438\u0442\u0435\u043b\u044c\u043d\u043e\u0433\u043e \u043f\u0430\u0434\u0435\u0436\u0430, \u043a\u043e\u0433\u0434\u0430 \u043f\u0440\u0435\u0434\u0438\u0446\u0438\u0440\u0443\u0449\u0438\u0439 \u043a\u043e\u043c\u043f\u043e\u043d\u0435\u043d\u0442 \u043e\u043f\u0440\u0435\u0434\u0435\u043b\u0435\u043d\n\u0441\u043e\u0447\u0435\u0442\u0430\u043d\u0438\u0435\u043c {\u043f\u0440\u0438\u043b\u0430\u0433\u0430\u0442\u0435\u043b\u044c\u043d\u043e\u0435 + \u0441\u0443\u0449\u0435\u0441\u0442\u0432\u0438\u0442\u0435\u043b\u044c\u043d\u043e\u0435}; 3. \u0432 \u044d\u043a\u0441\u043f\u043b\u0438\u0446\u0438\u0442\u043d\u043e\u0439 \u0444\u043e\u0440\u043c\u0435 \u043a\u043e\u043d\u0441\u0442\u0440\u0443\u043a\u0446\u0438\u0435\u0439 \u0442\u0438\u043f\u0430 \u00ab\u043e\u0431\u044a\u0435\u043a\u0442 \u043c\u043e\u0436\u0435\u0442 \u0438\u043c\u0435\u0442\u044c \u0442\u0430\u043a\u0438\u0435 {\u0445\u0430\u0440\u0430\u043a\u0442\u0435\u0440\u0438\u0441\u0442\u0438\u043a\u0438,\n\u0441\u0432\u043e\u0439\u0441\u0442\u0432\u0430, \u043f\u0440\u0438\u0437\u043d\u0430\u043a\u0438}\u00bb.\n4. \u0441 \u043f\u043e\u043c\u043e\u0449\u044c\u044e \u0441\u0432\u044f\u0437\u0430\u043d\u043d\u043e\u0439 \u0441\u0438\u043d\u0442\u0430\u043a\u0441\u0435\u043c\u044b \u0441 \u0440\u043e\u0434\u0438\u0442\u0435\u043b\u044c\u043d\u044b\u043c \u043f\u0430\u0434\u0435\u0436\u043e\u043c, \u043e\u0431\u043e\u0437\u043d\u0430\u0447\u0430\u044e\u0449\u0435\u0439 \u043e\u0431\u044a\u0435\u043a\u0442 \u043f\u0440\u0438 \u043e\u0442\u0433\u043b\u0430\u0433\u043e\u043b\u044c\u043d\u043e\u043c \u0441\u0443\u0449\u0435\u0441\u0442\u0432\u0438\u0442\u0435\u043b\u044c\u043d\u043e\u043c.\n\u041e\u0431\u043d\u0430\u0440\u0443\u0436\u0435\u043d\u0438\u0435 \u0441\u0438\u043d\u0442\u0430\u043a\u0441\u0438\u0447\u0435\u0441\u043a\u0438\u0445 \u0445\u0430\u0440\u0430\u043a\u0442\u0435\u0440\u0438\u0441\u0442\u0438\u043a \u0432\u044b\u043f\u043e\u043b\u043d\u044f\u0435\u0442\u0441\u044f \u043f\u0440\u0430\u0441\u0435\u0440\u043e\u043c \u0440\u0443\u0441\u0441\u043a\u043e\u0433\u043e \u044f\u0437\u044b\u043a\u0430 (\u0410\u041e\u0422-\u043f\u0430\u0440\u0441\u0435\u0440 [10]), \u0441\u043f\u043e\u0441\u043e\u0431\u043d\u044b\u043c \u0440\u0430\u0441\u043f\u043e\u0437\u043d\u0430\u0432\u0430\u0442\u044c \u0433\u0440\u0430\u043c\u043c\u0430\u0442\u0438\u0447\u0435\u0441\u043a\u0438\u0435 \u0444\u043e\u0440\u043c\u044b \u0432\u0441\u0442\u0440\u0435\u0447\u0430\u0435\u043c\u044b\u0445 \u0441\u043b\u043e\u0432. \u0414\u043b\u044f \u043f\u0440\u0430\u0432\u0438\u043b\u044c\u043d\u043e\u0439 \u0440\u0430\u0431\u043e\u0442\u044b \u043e\u043f\u0440\u0435\u0434\u0435\u043b\u044f\u0435\u0442\u0441\u044f \u0442\u0430\u043a\u0436\u0435 \u043f\u043e\u0440\u044f\u0434\u043e\u043a \u043f\u0440\u0438\u043c\u0435\u043d\u0435\u043d\u0438\u044f (\u043f\u0440\u0438\u043e\u0440\u0438\u0442\u0435\u0442) \u043f\u0440\u0430\u0432\u0438\u043b.\n\u041e\u043f\u0440\u0435\u0434\u0435\u043b\u044f\u044e\u0442\u0441\u044f \u0441\u0432\u043e\u0439\u0441\u0442\u0432\u0430 \u043a\u043e\u043d\u0446\u0435\u043f\u0442\u0430\n\u00ab\u043e\u0431\u043b\u0443\u0447\u0435\u043d\u0438\u0435\u00bb, \u0442.\u0435. \u0441\u0438\u0441\u0442\u0435\u043c\u0430 \u043f\u0440\u0438\u043c\u0435\u043d\u044f\u0435\u0442 \u043e\u043f\u0438\u0441\u0430\u043d\u043d\u044b\u0435 \u043f\u0440\u0430\u0432\u0438\u043b\u0430 \u0442\u043e\u043b\u044c\u043a\u043e \u043a \u0442\u0435\u043c \u043f\u0440\u0435\u0434\u043b\u043e\u0436\u0435\u043d\u0438\u044f\u043c, \u0432 \u043a\u043e\u0442\u043e\u0440\u044b\u0445 \u043e\u0431\u043d\u0430\u0440\u0443\u0436\u0438\u0442 \u043b\u044e\u0431\u0443\u044e \u0441\u043b\u043e\u0432\u043e\u0444\u043e\u0440\u043c\u0443 \u00ab\u043e\u0431\u043b\u0443\u0447\u0435\u043d\u0438\u0435\u00bb.\n\u0422\u0430\u043a\u0438\u043c \u043e\u0431\u0440\u0430\u0437\u043e\u043c, \u0438\u043c\u0435\u0435\u043c \u0432\u043e\u0437\u043c\u043e\u0436\u043d\u043e\u0441\u0442\u044c\n\u043e\u0431\u043d\u0430\u0440\u0443\u0436\u0438\u0442\u044c \u0432 \u0442\u0435\u043a\u0441\u0442\u0435 \u0438 \u0438\u0441\u0442\u043e\u043b\u043a\u043e\u0432\u0430\u0442\u044c, \u043d\u0430\u043f\u0440\u0438\u043c\u0435\u0440, \u0441\u043b\u0435\u0434\u0443\u044e\u0449\u0438\u0435 \u0441\u0432\u043e\u0439\u0441\u0442\u0432\u0430 \u0442\u0435\u0440\u043c\u0438\u043d\u0430:\n\u00ab\u2026\u043e\u0431\u043b\u0443\u0447\u0435\u043d\u0438\u044f \u0431\u043e\u043b\u044c\u0448\u043e\u0439 \u043c\u043e\u0449\u043d\u043e\u0441\u0442\u0438\u00bb  \u043f\u0440\u0430\u0432\u0438\u043b\u043e\n2; \u00ab\u043c\u043e\u0449\u043d\u043e\u0441\u0442\u044c\u00bb \u2013 \u0430\u0442\u0440\u0438\u0431\u0443\u0442 \u043a\u043e\u043d\u0446\u0435\u043f\u0442\u0430 \u00ab\u043e\u0431\u043b\u0443\u0447\u0435\u043d\u0438\u0435\u00bb;\n\u00ab\u2026\u043e\u0431\u043b\u0443\u0447\u0435\u043d\u0438\u0435 \u0432\u0441\u0435\u0433\u043e \u0442\u0435\u043b\u0430\u00bb  \u043f\u0440\u0430\u0432\u0438\u043b\u043e 4;\n\u043f\u0440\u0435\u0434\u0438\u043a\u0430\u0442 \u00ab\u043e\u0431\u043b\u0443\u0447\u0430\u0442\u044c\u00bb \u0438 \u0435\u0433\u043e \u043e\u0431\u044a\u0435\u043a\u0442 \u00ab\u0442\u0435\u043b\u043e\u00bb;\n\u041f\u0440\u0435\u0438\u043c\u0443\u0449\u0435\u0441\u0442\u0432\u043e\u043c \u043f\u0440\u0435\u0434\u043b\u0430\u0433\u0430\u0435\u043c\u043e\u0433\u043e \u043c\u0435\u0442\u043e\u0434\u0430\n\u044f\u0432\u043b\u044f\u0435\u0442\u0441\u044f \u0442\u043e, \u0447\u0442\u043e \u00ab\u0442\u043e\u0447\u043a\u0430\u043c\u0438 \u0432\u0445\u043e\u0434\u0430\u00bb \u0434\u043b\u044f \u0430\u043d\u0430\u043b\u0438\u0437\u0430 \u0442\u0435\u043a\u0441\u0442\u0430 \u043c\u043e\u0433\u0443\u0442 \u0441\u043b\u0443\u0436\u0438\u0442\u044c \u0438 \u0441\u043b\u043e\u0432\u0430 \u0438 \u0441\u043e\u0431\u0441\u0442\u0432\u0435\u043d\u043d\u043e \u0441\u0438\u043d\u0442\u0430\u043a\u0441\u0435\u043c\u044b.\n\u0421\u0442\u0440\u0443\u043a\u0442\u0443\u0440\u0430 \u0418\u0421 \u043f\u0440\u0435\u0434\u0441\u0442\u0430\u0432\u043b\u0435\u043d\u0430 \u043d\u0430 \u0440\u0438\u0441.1:\n\u0420\u0438\u0441.1. \u0424\u0440\u0435\u0439\u043c\u0432\u043e\u0440\u043a \u0418\u0421 \u043d\u0430 \u043e\u0441\u043d\u043e\u0432\u0435 \u0441\u0438\u043d\u0442\u0430\u043a\u0441\u0435\u043c\n\u0418\u0421 \u0441\u043e\u0441\u0442\u043e\u0438\u0442 \u0438\u0437 \u0441\u043b\u0435\u0434\u0443\u044e\u0449\u0438\u0445 \u043c\u043e\u0434\u0443\u043b\u0435\u0439: \u041c\u043e\u0434\u0443\u043b\u044c \u0431\u0430\u0437\u043e\u0432\u043e\u0439 \u043e\u043d\u0442\u043e\u043b\u043e\u0433\u0438\u0438 (\u0411\u041e) \u043f\u043e\u0441\u0442\u0440\u043e\u0435\u043d\n\u0432\u0440\u0443\u0447\u043d\u0443\u044e \u0441 \u043f\u043e\u043c\u043e\u0449\u044c\u044e \u044d\u043a\u0441\u043f\u0435\u0440\u0442\u0430 \u041f\u041e.\u0412 \u043d\u0430\u0441\u0442\u043e\u044f\u0449\u0438\u0439 \u043c\u043e\u043c\u0435\u043d\u0442 \u0431\u0430\u0437\u043e\u0432\u0430\u044f \u043e\u043d\u0442\u043e\u043b\u043e\u0433\u0438\u044f, \u043f\u0440\u0435\u0434\u0441\u0442\u0430\u0432\u043b\u0435\u043d\u043d\u0430\u044f \u043d\u0430 OWL \u0441\u043e\u0434\u0435\u0440\u0436\u0438\u0442 \u043e\u043a\u043e\u043b\u043e 30 \u043a\u043e\u043d\u0446\u0435\u043f\u0442\u043e\u0432 \u0438 \u043e\u043f\u0438\u0441\u044b\u0432\u0430\u044e\u0449\u0438\u0445 \u0438\u0445 \u043e\u0442\u043d\u043e\u0448\u0435\u043d\u0438\u0439. \u0411\u041e \u043e\u0434\u043d\u043e\u0432\u0440\u0435\u043c\u0435\u043d\u043d\u043e \u0441\u043b\u0443\u0436\u0438\u0442 \u00ab\u0444\u0438\u043b\u044c\u0442\u0440\u043e\u043c\u00bb \u0434\u043b\u044f \u043e\u0442\u0431\u043e\u0440\u0430 \u0444\u0440\u0430\u0433\u043c\u0435\u043d\u0442\u043e\u0432 \u0442\u0435\u043a\u0441\u0442\u0430, \u043f\u043e\u0442\u0435\u043d\u0446\u0438\u0430\u043b\u044c\u043d\u043e \u0441\u043e\u0434\u0435\u0440\u0436\u0430\u0449\u0438\u0445 \u0438\u043d\u0444\u043e\u0440\u043c\u0430\u0446\u0438\u044e, \u043a\u043e\u0442\u043e\u0440\u0430\u044f \u043f\u043e\u0437\u0432\u043e\u043b\u0438\u0442 \u043b\u0438\u0431\u043e \u0434\u043e\u0431\u0430\u0432\u0438\u0442\u044c \u043d\u043e\u0432\u044b\u0435 \u0441\u0432\u043e\u0439\u0441\u0442\u0432\u0430 \u0434\u043b\u044f \u0441\u0443\u0449\u0435\u0441\u0442\u0432\u0443\u044e\u0449\u0438\u0445 \u043a\u043e\u043d\u0446\u0435\u043f\u0442\u043e\u0432 \u0411\u041e, \u043b\u0438\u0431\u043e \u0434\u043e\u0431\u0430\u0432\u0438\u0442\u044c \u043d\u043e\u0432\u044b\u0435 \u043a\u043e\u043d\u0446\u0435\u043f\u0442\u044b \u0432 \u0411\u041e (\u0441 \u0438\u0445 \u0441\u0432\u043e\u0439\u0441\u0442\u0432\u0430\u043c\u0438) \u0438 \u043f\u043e\u043b\u0443\u0447\u0438\u0442\u044c \u0440\u0430\u0441\u0448\u0438\u0440\u0435\u043d\u043d\u0443\u044e \u043e\u043d\u0442\u043e\u043b\u043e\u0433\u0438\u044e (\u0420\u041e).\n\u041c\u043e\u0434\u0443\u043b\u044c \u043b\u0438\u043d\u0433\u0432\u0438\u0441\u0442\u0438\u0447\u0435\u0441\u043a\u043e\u0439 \u0440\u0430\u0437\u043c\u0435\u0442\u043a\u0438, \u043e\u0441\u043d\u043e\u0432\u043e\u0439\n\u043a\u043e\u0442\u043e\u0440\u043e\u0433\u043e \u0441\u043b\u0443\u0436\u0438\u0442 \u043f\u0430\u0440\u0441\u0435\u0440 \u044f\u0437\u044b\u043a\u0430. \u041d\u0430 \u0432\u044b\u0445\u043e\u0434\u0435 \u044d\u0442\u043e\u0433\u043e \u043c\u043e\u0434\u0443\u043b\u044f \u043f\u043e\u043b\u0443\u0447\u0430\u0435\u043c \u0444\u0440\u0430\u0433\u043c\u0435\u043d\u0442\u044b \u0442\u0435\u043a\u0441\u0442\u0430, \u0441\u043d\u0430\u0431\u0436\u0435\u043d\u043d\u044b\u0435 \u043d\u0435\u043e\u0431\u0445\u043e\u0434\u0438\u043c\u043e\u0439 \u0441\u0438\u043d\u0442\u0430\u043a\u0441\u0438\u0447\u0435\u0441\u043a\u043e\u0439 \u0438\u043d\u0444\u043e\u0440\u043c\u0430\u0446\u0438\u0435\u0439 \u0434\u043b\u044f \u0434\u0430\u043b\u044c\u043d\u0435\u0439\u0448\u0435\u0439 \u043e\u0431\u0440\u0430\u0431\u043e\u0442\u043a\u0438.\n\u041c\u043e\u0434\u0443\u043b\u044c \u0441\u0438\u043d\u0442\u0430\u043a\u0441\u0435\u043c \u0440\u0443\u0441\u0441\u043a\u043e\u0433\u043e \u044f\u0437\u044b\u043a\u0430 (\u043e\u0441\u043d\u043e\u0432\u043d\u043e\u0439\n\u043c\u043e\u0434\u0443\u043b\u044c \u0418\u0421), \u0432\u043a\u043b\u044e\u0447\u0430\u044e\u0449\u0438\u0439 \u0432 \u0441\u0435\u0431\u044f \u0441\u043b\u043e\u0432\u0430\u0440\u044c \u0442\u0438\u043f\u0430 WordNet (\u0430\u043d\u0430\u043b\u043e\u0433\u0438 \u0434\u043b\u044f \u0440\u0443\u0441\u0441\u043a\u043e\u0433\u043e \u044f\u0437\u044b\u043a\u0430 RuNet, RussNet), \u043e\u0431\u044a\u0435\u0434\u0438\u043d\u044f\u044e\u0449\u0438\u0439 \u0441\u043b\u043e\u0432\u0430 \u0432 \u0433\u0440\u0443\u043f\u043f\u044b \u0441\u0438\u043d\u043e\u043d\u0438\u043c\u043e\u0432.\n\u041c\u043e\u0434\u0443\u043b\u044c \u043d\u043e\u0440\u043c\u0430\u043b\u0438\u0437\u0430\u0446\u0438\u0438 \u0441\u0432\u043e\u0439\u0441\u0442\u0432,\n\u043f\u0440\u0435\u043e\u0431\u0440\u0430\u0437\u0443\u044e\u0449\u0438\u0439 \u043d\u0430\u0439\u0434\u0435\u043d\u043d\u044b\u0435 \u043d\u0430 \u043f\u0440\u0435\u0434\u044b\u0434\u0443\u0449\u0435\u043c \u044d\u0442\u0430\u043f\u0435 \u0434\u0430\u043d\u043d\u044b\u0435 \u0432 \u0444\u043e\u0440\u043c\u0430\u043b\u044c\u043d\u043e\u0435 \u043f\u0440\u0435\u0434\u0441\u0442\u0430\u0432\u043b\u0435\u043d\u0438\u0435 \u043d\u0430 OWL \u0438 \u043e\u0431\u0435\u0441\u043f\u0435\u0447\u0438\u0432\u0430\u044e\u0449\u0438\u0439 \u0440\u0430\u0441\u0448\u0438\u0440\u0435\u043d\u0438\u0435 \u0411\u041e.\n\u0417\u0430\u043a\u043b\u044e\u0447\u0435\u043d\u0438\u0435\n\u0410\u043d\u0430\u043b\u0438\u0437 \u0442\u0435\u043a\u0441\u0442\u043e\u0432\u043e\u0439 \u0438\u043d\u0444\u043e\u0440\u043c\u0430\u0446\u0438\u0438 \u0438 \u0438\u0437\u0432\u043b\u0435\u0447\u0435\u043d\u0438\u0435 \u0438\u0437\n\u043f\u043e\u043b\u043d\u043e\u0442\u0435\u043a\u0441\u0442\u043e\u0432\u044b\u0445 \u0434\u043e\u043a\u0443\u043c\u0435\u043d\u0442\u043e\u0432 \u0440\u0435\u043b\u0435\u0432\u0430\u043d\u0442\u043d\u044b\u0445 \u0434\u0430\u043d\u043d\u044b\u0445 \u043e\u0441\u0442\u0430\u0435\u0442\u0441\u044f \u0430\u043a\u0442\u0443\u0430\u043b\u044c\u043d\u043e\u0439 \u0437\u0430\u0434\u0430\u0447\u0435\u0439 \u043e\u043d\u0442\u043e\u043b\u043e\u0433\u0438\u0447\u0435\u0441\u043a\u043e\u0433\u043e \u0438\u043d\u0436\u0438\u043d\u0438\u0440\u0438\u043d\u0433\u0430 \u0432 \u0447\u0430\u0441\u0442\u043d\u043e\u0441\u0442\u0438. \u041a\u0430\u0447\u0435\u0441\u0442\u0432\u0435\u043d\u043d\u043e\u0435 \u0440\u0430\u0441\u0448\u0438\u0440\u0435\u043d\u0438\u0435 \u0432\u043e\u0437\u043c\u043e\u0436\u043d\u043e\u0441\u0442\u0435\u0439 \u0418\u0421 \u0432\u043e\u0437\u043c\u043e\u0436\u043d\u043e \u043f\u0440\u0438 \u0443\u0441\u043b\u043e\u0432\u0438\u0438 \u0432\u043d\u0435\u0434\u0440\u0435\u043d\u0438\u044f \u0432 \u043d\u0438\u0445 \u043c\u043e\u0434\u0443\u043b\u0435\u0439, \u0441\u043f\u043e\u0441\u043e\u0431\u043d\u044b\u0445 \u0438\u0437\u0432\u043b\u0435\u043a\u0430\u0442\u044c \u0445\u0430\u0440\u0430\u043a\u0442\u0435\u0440\u0438\u0441\u0442\u0438\u043a\u0438 \u043a\u043e\u043d\u0446\u0435\u043f\u0442\u043e\u0432 \u043d\u0430 \u043e\u0441\u043d\u043e\u0432\u0435 \u043b\u0438\u043d\u0433\u0432\u0438\u0441\u0442\u0438\u0447\u0435\u0441\u043a\u043e\u0433\u043e \u0430\u043d\u0430\u043b\u0438\u0437\u0430. \u041e\u0434\u043d\u0438\u043c \u0438\u0437 \u0432\u043e\u0437\u043c\u043e\u0436\u043d\u044b\u0445 \u0441\u043f\u043e\u0441\u043e\u0431\u043e\u0432 \u0440\u0435\u0448\u0435\u043d\u0438\u044f \u044d\u0442\u043e\u0439 \u0437\u0430\u0434\u0430\u0447\u0438 \u044f\u0432\u043b\u044f\u0435\u0442\u0441\u044f \u0438\u0441\u043f\u043e\u043b\u044c\u0437\u043e\u0432\u0430\u043d\u0438\u0435 \u043b\u0438\u043d\u0433\u0432\u0438\u0441\u0442\u0438\u0447\u0435\u0441\u043a\u0438\u0445 \u0448\u0430\u0431\u043b\u043e\u043d\u043e\u0432. \u0412 \u0434\u0430\u043d\u043d\u043e\u0439 \u0440\u0430\u0431\u043e\u0442\u0435 \u043f\u0440\u0435\u0434\u043b\u043e\u0436\u0435\u043d \u043f\u043e\u0434\u0445\u043e\u0434 \u043a \u0430\u0432\u0442\u043e\u043c\u0430\u0442\u0438\u0437\u0438\u0440\u043e\u0432\u0430\u043d\u043d\u043e\u043c\u0443 \u043f\u043e\u0441\u0442\u0440\u043e\u0435\u043d\u0438\u044e (\u0440\u0430\u0441\u0448\u0438\u0440\u0435\u043d\u0438\u044e) \u0431\u0430\u0437\u043e\u0432\u043e\u0439 \u043e\u043d\u0442\u043e\u043b\u043e\u0433\u0438\u0438 \u043d\u0430 \u043e\u0441\u043d\u043e\u0432\u0435 \u0441\u0438\u043d\u0442\u0430\u043a\u0441\u0435\u043c \u0440\u0443\u0441\u0441\u043a\u043e\u0433\u043e \u044f\u0437\u044b\u043a\u0430. \u041f\u043e\u0441\u043a\u043e\u043b\u044c\u043a\u0443 \u043a\u0430\u0436\u0434\u0430\u044f \u0441\u0438\u043d\u0442\u0430\u043a\u0441\u0435\u043c\u0430 \u043e\u043f\u0438\u0441\u044b\u0432\u0430\u0435\u0442\u0441\u044f \u043a\u043e\u043d\u0435\u0447\u043d\u044b\u043c \u0434\u0435\u0442\u0435\u0440\u043c\u0438\u043d\u0438\u0440\u043e\u0432\u0430\u043d\u043d\u044b\u043c \u043c\u043d\u043e\u0436\u0435\u0441\u0442\u0432\u043e\u043c \u043f\u0440\u0438\u0437\u043d\u0430\u043a\u043e\u0432, \u0442\u0430\u043a\u043e\u0439 \u043f\u043e\u0434\u0445\u043e\u0434 \u044f\u0432\u043b\u044f\u0435\u0442\u0441\u044f \u043d\u0435 \u0442\u043e\u043b\u044c\u043a\u043e \u0432\u043e\u0437\u043c\u043e\u0436\u043d\u044b\u043c, \u043d\u043e \u0438 \u043f\u0440\u0435\u0434\u043f\u043e\u0447\u0442\u0438\u0442\u0435\u043b\u044c\u043d\u044b\u043c, \u043f\u043e\u0441\u043a\u043e\u043b\u044c\u043a\u0443 \u043e\u043d \u043e\u0431\u0435\u0441\u043f\u0435\u0447\u0438\u0432\u0430\u0435\u0442 \u043e\u0434\u043d\u043e\u0437\u043d\u0430\u0447\u043d\u043e\u0435 \u043e\u043f\u0440\u0435\u0434\u0435\u043b\u0435\u043d\u0438\u0435 \u0441\u0432\u043e\u0439\u0441\u0442\u0432 \u043a\u043e\u043d\u0446\u0435\u043f\u0442\u043e\u0432 \u0441\u043e\u0437\u0434\u0430\u0432\u0430\u0435\u043c\u043e\u0439 \u043e\u043d\u0442\u043e\u043b\u043e\u0433\u0438\u0438. \u0422\u0440\u0443\u0434\u043e\u0435\u043c\u043a\u043e\u0441\u0442\u044c \u0437\u0430\u0434\u0430\u0447\u0438 \u043e\u043a\u0443\u043f\u0430\u0435\u0442\u0441\u044f \u043a\u0430\u0447\u0435\u0441\u0442\u0432\u043e\u043c \u043f\u043e\u043b\u0443\u0447\u0430\u0435\u043c\u044b\u0445 \u0440\u0435\u0437\u0443\u043b\u044c\u0442\u0430\u0442\u043e\u0432. \u0412 \u0431\u0443\u0434\u0443\u0449\u0435\u043c \u043f\u043b\u0430\u043d\u0438\u0440\u0443\u0435\u0442\u0441\u044f \u043f\u0440\u043e\u0432\u0435\u0440\u043a\u0430 \u044d\u0444\u0444\u0435\u043a\u0442\u0438\u0432\u043d\u043e\u0441\u0442\u0438 \u043c\u0435\u0442\u043e\u0434\u0430 \u043d\u0430 \u0431\u043e\u043b\u044c\u0448\u043e\u043c \u043a\u043e\u0440\u043f\u0443\u0441\u0435, \u0430 \u0442\u0430\u043a\u0436\u0435 \u0432\u043e\u0437\u043c\u043e\u0436\u043d\u043e\u0441\u0442\u044c \u0435\u0433\u043e \u043f\u0440\u0438\u043c\u0435\u043d\u0435\u043d\u0438\u044f \u0434\u043b\u044f \u0430\u043d\u0430\u043b\u0438\u0437\u0430 \u0442\u0435\u043a\u0441\u0442\u043e\u0432 \u043d\u0430 \u0434\u0440\u0443\u0433\u0438\u0445 \u044f\u0437\u044b\u043a\u0430\u0445 (\u0430\u0433\u043b\u0438\u0439\u0441\u043a\u0438\u0439, \u0444\u0440\u0430\u043d\u0446\u0443\u0437\u0441\u043a\u0438\u0439).\n\u041b\u0438\u0442\u0435\u0440\u0430\u0442\u0443\u0440\u0430\n[1] Charlet, J., at al. Apport des outils de TAL a la\nconstruction d\u2019ontologies : propositions au sein de la plateforme DaFOE/ Charlet, J., at al dans TALN 2009, Senlis, 24\u201326 juin 2009. [2] AI3\u2019s Inaugural State of Tooling for Semantic\nTechnologies/ Adaptive Information Adaptive\nInnovation Adaptive Infrastructure //URL\nhttp://www.mkbergman.com/991/the-state-oftooling-for-semantic-technologies.\n[3] Simperl E., Mochol M. Achieving Maturity: the\nState of Practice in Ontology Engineering in 2009. // In International Journal of Computer Science and Applications, Technomathematics Research Foundation. 2010. Vol. 7 No. 1, P. 45\u2013 65.\n[4] De Nicola, A., & all. A software engineering\napproach to ontology building. // In Information\nSystems 34. 2009. P. 258\u2013275. [5] Makki J., Alquier A.-M., Prince V. Semi\nAutomatic Ontology Instantiation in the domain of Risk Management. // In IFIP, Advances in Information and Communication Technology. 2008. Volume 288. P. 254-265.\n[6] Buitelaar P., Cimiano P., and Magnini B.\nOntology Learning from Texts : An Overview./In Ontology Learning from Text: Methods, Evaluation and Applications. / P. Buitelaar, P. Cimmiano, and B. Magnini, Eds. IOS Press. 2008.\n[7] Zhou, L. Ontology Learning: State of the Art\nand Open Issues. // Information Technology and Management. 2007. 8(3), P.241-252.\n[8] Hearst, M.A., Automatic Acquisition of\nHyponyms from Large Text Corpora. //In: Proceedings of the 14th International Conference on Computational Linguistics. 1992. P 539-545.\n[9] \u0417\u043e\u043b\u043e\u0442\u043e\u0432\u0430 \u0413.\u0410. \u0421\u0438\u043d\u0442\u0430\u043a\u0441\u0438\u0447\u0435\u0441\u043a\u0438\u0439 \u0441\u043b\u043e\u0432\u0430\u0440\u044c:\n\u0420\u0435\u043f\u0435\u0440\u0442\u0443\u0430\u0440 \u044d\u043b\u0435\u043c\u0435\u043d\u0442\u0430\u0440\u044b\u0445 \u0435\u0434\u0438\u043d\u0438\u0446 \u0440\u0443\u0441\u0441\u043a\u043e\u0433\u043e \u0441\u0438\u043d\u0442\u0430\u043a\u0441\u0438\u0441\u0430. \u0415\u0434\u0438\u0442\u043e\u0440\u0438\u0430\u043b \u0423\u0420\u0421\u0421, 2011.\n[10] \u041f\u0440\u043e\u0435\u043a\u0442 \u0410\u041e\u0422// URL:\nhttp://aot.ru/demo/morph.html\nAutomatic Method Of Domain Ontology\nConstruction based on Characteristics of\nCorpora POS-Analysis\nO. Oroinska\nIt is now widely recognized that ontologies,\nare one of the fundamental cornerstones of knowledge-based systems. What is lacking, however, is a currently accepted strategy of how to build ontology; what kinds of the resources and techniques are indispensables to optimize the expenses and the time on the one hand and the amplitude, the completeness, the robustness of en ontology on the other hand. The paper offers a semi-automatic ontology construction method from text corpora in the domain of radiological protection. This method is composed from next steps: 1) text annotation with part-of-speech tags; 2) revelation of the significant linguistic structures and forming the templates; 3) search of text fragments corresponding to these templates; 4) basic ontology instantiation process."}], "references": [{"title": "Apport des outils de TAL a la construction d\u2019ontologies : propositions au sein de la plateforme DaFOE/ Charlet, J., at al dans TALN 2009, Senlis", "author": ["J. Charlet", "at al"], "venue": "juin", "citeRegEx": "1", "shortCiteRegEx": "1", "year": 2009}, {"title": "Achieving Maturity: the State of Practice in Ontology Engineering", "author": ["E. Simperl", "M. Mochol"], "venue": "In International Journal of Computer Science and Applications, Technomathematics Research Foundation", "citeRegEx": "3", "shortCiteRegEx": "3", "year": 2009}, {"title": "A software engineering approach to ontology building", "author": ["A. De Nicola"], "venue": "Information Systems", "citeRegEx": "4", "shortCiteRegEx": "4", "year": 2009}, {"title": "Semi Automatic Ontology Instantiation in the domain of Risk Management", "author": ["J. Makki", "A.-M. Alquier", "V. Prince"], "venue": "IFIP, Advances in Information and Communication Technology", "citeRegEx": "5", "shortCiteRegEx": "5", "year": 2008}, {"title": "Ontology Learning from Texts : An Overview./In Ontology Learning from Text: Methods, Evaluation and Applications", "author": ["P. Buitelaar", "P. Cimiano", "B. Magnini"], "venue": null, "citeRegEx": "6", "shortCiteRegEx": "6", "year": 2008}, {"title": "Ontology Learning: State of the Art and Open Issues", "author": ["L. Zhou"], "venue": "Information Technology and Management", "citeRegEx": "7", "shortCiteRegEx": "7", "year": 2007}, {"title": "Automatic Acquisition of Hyponyms from Large Text Corpora", "author": ["M.A. Hearst"], "venue": "//In: Proceedings of the 14th International Conference on Computational Linguistics", "citeRegEx": "8", "shortCiteRegEx": "8", "year": 1992}], "referenceMentions": [{"referenceID": 1, "context": "\u0421\u043e \u0441\u0441\u044b\u043b\u043a\u043e\u0439 \u043d\u0430 [2],[3] \u043c\u043e\u0436\u043d\u043e \u0443\u0442\u0432\u0435\u0440\u0436\u0434\u0430\u0442\u044c, \u0447\u0442\u043e \u0432 2011 \u0433.", "startOffset": 18, "endOffset": 21}, {"referenceID": 2, "context": "\u041e\u0431\u043e\u0431\u0449\u0430\u044f \u043c\u043d\u043e\u0436\u0435\u0441\u0442\u0432\u043e \u0441\u0445\u043e\u0434\u043d\u044b\u0445 \u043e\u043f\u0440\u0435\u0434\u0435\u043b\u0435\u043d\u0438\u0439, \u043d\u0430\u043f\u043e\u043c\u043d\u0438\u043c, \u0447\u0442\u043e \u0432 \u043d\u0430\u0441\u0442\u043e\u044f\u0449\u0435\u0435 \u0432\u0440\u0435\u043c\u044f \u043f\u043e\u0434 \u043e\u043d\u0442\u043e\u043b\u043e\u0433\u0438\u0435\u0439 \u043f\u043e\u0434\u0440\u0430\u0437\u0443\u043c\u0430\u0435\u0432\u0430\u0435\u0442\u0441\u044f \u0441\u0435\u043c\u0430\u043d\u0442\u0438\u0447\u0435\u0441\u043a\u0430\u044f \u0441\u0442\u0440\u0443\u043a\u0442\u0443\u0440\u0430, \u0432 \u044f\u0432\u043d\u043e\u043c \u0432\u0438\u0434\u0435 \u043e\u043f\u0438\u0441\u044b\u0432\u0430\u044e\u0449\u0430\u044f \u043e\u0441\u043d\u043e\u0432\u043d\u044b\u0435 \u043f\u043e\u043d\u044f\u0442\u0438\u044f (\u043a\u043e\u043d\u0446\u0435\u043f\u0442\u044b) \u043f\u0440\u0435\u0434\u043c\u0435\u0442\u043d\u043e\u0439 \u043e\u0431\u043b\u0430\u0441\u0442\u0438 (\u041f\u041e), \u0441\u0432\u044f\u0437\u044b\u0432\u0430\u044e\u0449\u0438\u0435 \u0438\u0445 \u043e\u0442\u043d\u043e\u0448\u0435\u043d\u0438\u044f, \u0430 \u0442\u0430\u043a\u0436\u0435 \u0430\u043a\u0441\u0438\u043e\u043c\u044b, \u043e\u043f\u0438\u0441\u044b\u0432\u0430\u044e\u0449\u0438\u0435 \u043f\u0440\u0430\u0432\u0438\u043b\u0430 \u0432\u044b\u0432\u043e\u0434\u0430 \u043d\u043e\u0432\u044b\u0445 \u043a\u043e\u043d\u0446\u0435\u043f\u0442\u043e\u0432 [4].", "startOffset": 292, "endOffset": 295}, {"referenceID": 3, "context": "\u0421 \u043f\u043e\u044f\u0432\u043b\u0435\u043d\u0438\u0435\u043c \u0441\u0435\u0442\u0435\u0432\u044b\u0445 \u043b\u0435\u043a\u0441\u0438\u0447\u0435\u0441\u043a\u0438\u0445 \u0440\u0435\u0441\u0443\u0440\u0441\u043e\u0432 \u0438 \u0441\u043e\u0432\u0435\u0440\u0448\u0435\u043d\u0441\u0442\u0432\u043e\u0432\u0430\u043d\u0438\u0435\u043c \u0441\u0438\u043d\u0442\u0430\u043a\u0441\u0438\u0447\u0435\u0441\u043a\u0438\u0445 \u0430\u043d\u0430\u043b\u0438\u0437\u0430\u0442\u043e\u0440\u043e\u0432 \u043b\u0438\u043d\u0432\u0438\u0441\u0442\u0438\u0447\u0435\u0441\u043a\u0438\u0435 \u043c\u0435\u0442\u043e\u0434\u044b \u043f\u0440\u0438\u0432\u043b\u0435\u043a\u0430\u044e\u0442 \u0432\u0441\u0435 \u0431\u043e\u043b\u044c\u0448\u0435\u0435 \u0432\u043d\u0438\u043c\u0430\u043d\u0438\u0435 \u0441\u043f\u0435\u0446\u0438\u0430\u043b\u0438\u0441\u0442\u043e\u0432 \u0431\u043b\u0430\u0433\u043e\u0434\u0430\u0440\u044f \u0432\u044b\u0441\u043e\u043a\u043e\u043c\u0443 \u043a\u0430\u0447\u0435\u0441\u0442\u0432\u0443 \u0440\u0435\u0437\u0443\u043b\u044c\u0442\u0430\u0442\u043e\u0432, \u043a\u043e\u0442\u043e\u0440\u044b\u0435 \u043e\u0431\u0435\u0449\u0430\u044e\u0442 \u0442\u0430\u043a\u0438\u0435 \u043c\u0435\u0442\u043e\u0434\u044b [5].", "startOffset": 228, "endOffset": 231}, {"referenceID": 4, "context": "[6],", "startOffset": 0, "endOffset": 3}, {"referenceID": 5, "context": "\u0441\u0440\u0430\u0432\u043d\u0435\u043d\u0438\u044e \u0441 \u0440\u0435\u0437\u0443\u043b\u044c\u0442\u0430\u0442\u0430\u043c\u0438 \u0440\u0430\u0431\u043e\u0442\u044b \u044d\u043a\u0441\u043f\u0435\u0440\u0442\u043e\u0432 [7]).", "startOffset": 42, "endOffset": 45}, {"referenceID": 6, "context": "Hearst [8].", "startOffset": 7, "endOffset": 10}, {"referenceID": 4, "context": "\u041c\u0430\u0442\u0435\u043c\u0430\u0442\u0438\u0447\u0435\u0441\u043a\u0438 \u043e\u043d\u0442\u043e\u043b\u043e\u0433\u0438\u044f \u043e\u043f\u0440\u0435\u0434\u0435\u043b\u044f\u0435\u0442\u0441\u044f \u0441\u043b\u0435\u0434\u0443\u044e\u0449\u0438\u043c \u043e\u0431\u0440\u0430\u0437\u043e\u043c [6]:", "startOffset": 55, "endOffset": 58}, {"referenceID": 4, "context": "\u041f\u0430\u0440\u0441\u0435\u0440\u044b \u044f\u0437\u044b\u043a\u0430 (\u043d\u0430\u043f\u0440\u0438\u043c\u0435\u0440, \u043f\u0440\u043e\u0435\u043a\u0442 \u0410\u041e\u0422 [6]) \u043c\u043e\u0433\u0443\u0442 \u0431\u044b\u0442\u044c \u0443\u0441\u043f\u0435\u0448\u043d\u043e \u0438\u0441\u043f\u043e\u043b\u044c\u0437\u043e\u0432\u0430\u043d\u044b \u043a\u0430\u043a \u0434\u043b\u044f \u043e\u043f\u0440\u0435\u0434\u0435\u043b\u0435\u043d\u0438\u044f \u0440\u043e\u043b\u0435\u0439 \u043a\u043e\u043d\u0446\u0435\u043f\u0442\u043e\u0432, \u0442\u0430\u043a \u0438 \u0434\u043b\u044f \u043e\u043f\u0440\u0435\u0434\u0435\u043b\u0435\u043d\u0438\u044f \u0438\u0445 \u0430\u0442\u0440\u0438\u0431\u0443\u0442\u043e\u0432.", "startOffset": 36, "endOffset": 39}, {"referenceID": 6, "context": "[8] \u0438 \u0436\u0434\u0435\u0442 \u0434\u043e\u0441\u0442\u043e\u0439\u043d\u043e\u0439 \u0442\u0435\u0445\u043d\u0438\u0447\u0435\u0441\u043a\u043e\u0439 \u0440\u0435\u0430\u043b\u0438\u0437\u0430\u0446\u0438\u0438.", "startOffset": 0, "endOffset": 3}, {"referenceID": 0, "context": "[1] Charlet, J.", "startOffset": 0, "endOffset": 3}, {"referenceID": 1, "context": "[3] Simperl E.", "startOffset": 0, "endOffset": 3}, {"referenceID": 2, "context": "[4] De Nicola, A.", "startOffset": 0, "endOffset": 3}, {"referenceID": 3, "context": "[5] Makki J.", "startOffset": 0, "endOffset": 3}, {"referenceID": 4, "context": "[6] Buitelaar P.", "startOffset": 0, "endOffset": 3}, {"referenceID": 5, "context": "[7] Zhou, L.", "startOffset": 0, "endOffset": 3}, {"referenceID": 6, "context": "[8] Hearst, M.", "startOffset": 0, "endOffset": 3}], "year": 2014, "abstractText": "\u0412\u044b\u0437\u043e\u0432 \u0441\u0435\u0433\u043e\u0434\u043d\u044f\u0448\u043d\u0435\u0433\u043e \u0434\u043d\u044f, \u043e\u0431\u0443\u0441\u043b\u043e\u0432\u043b\u0435\u043d\u043d\u044b\u0439 \u0431\u0443\u0440\u043d\u044b\u043c \u0440\u043e\u0441\u0442\u043e\u043c \u0442\u0435\u043a\u0441\u0442\u043e\u0432\u044b\u0445 \u0445\u0440\u0430\u043d\u0438\u043b\u0438\u0449 \u0432 \u0433\u043b\u043e\u0431\u0430\u043b\u044c\u043d\u043e\u0439 \u0441\u0435\u0442\u0438 \u0418\u043d\u0442\u0435\u0440\u043d\u0435\u0442, \u0437\u0430\u043a\u043b\u044e\u0447\u0430\u0435\u0442\u0441\u044f \u0432 \u0442\u043e\u043c, \u0447\u0442\u043e\u0431\u044b \u00ab\u043d\u0430\u0443\u0447\u0438\u0442\u044c\u00bb \u0441\u0430\u043c\u0438 \u0438\u043d\u0444\u043e\u0440\u043c\u0430\u0446\u0438\u043e\u043d\u043d\u044b\u0435 \u0441\u0438\u0441\u0442\u0435\u043c\u044b (\u0418\u0421) \u043e\u0431\u043d\u0430\u0440\u0443\u0436\u0438\u0432\u0430\u0442\u044c \u0438 \u043f\u0440\u0430\u0432\u0438\u043b\u044c\u043d\u043e \u0438\u043d\u0442\u0435\u0440\u043f\u0440\u0435\u0442\u0438\u0440\u043e\u0432\u0430\u0442\u044c \u043f\u043e\u043b\u0435\u0437\u043d\u0443\u044e \u0438\u043d\u0444\u043e\u0440\u043c\u0430\u0446\u0438\u044e, \u043f\u0440\u0435\u0434\u043e\u0441\u0442\u0430\u0432\u043b\u044f\u0435\u043c\u0443\u044e \u0442\u0435\u043a\u0441\u0442\u043e\u043c. \u0420\u0430\u0437\u0440\u0430\u0431\u043e\u0442\u043a\u0430 \u043c\u0435\u0442\u043e\u0434\u043e\u0432 \u0430\u0432\u0442\u043e\u043c\u0430\u0442\u0438\u0447\u0435\u0441\u043a\u043e\u0433\u043e \u0430\u043d\u0430\u043b\u0438\u0437\u0430 \u0442\u0435\u043a\u0441\u0442\u043e\u0432\u043e\u0439 \u0438\u043d\u0444\u043e\u0440\u043c\u0430\u0446\u0438\u0438 \u0438 \u0438\u0437\u0432\u043b\u0435\u0447\u0435\u043d\u0438\u0435 \u0438\u0437 \u043f\u043e\u043b\u043d\u043e\u0442\u0435\u043a\u0441\u0442\u043e\u0432\u044b\u0445 \u0434\u043e\u043a\u0443\u043c\u0435\u043d\u0442\u043e\u0432 \u0440\u0435\u043b\u0435\u0432\u0430\u043d\u0442\u043d\u044b\u0445 \u0434\u0430\u043d\u043d\u044b\u0445 \u044f\u0432\u043b\u044f\u0435\u0442\u0441\u044f \u0430\u043a\u0442\u0443\u0430\u043b\u044c\u043d\u043e\u0439 \u0437\u0430\u0434\u0430\u0447\u0435\u0439 \u0438\u043d\u0436\u0435\u043d\u0435\u0440\u0438\u0438 \u0437\u043d\u0430\u043d\u0438\u0439 \u0432 \u0446\u0435\u043b\u043e\u043c \u0438 \u043e\u043d\u0442\u043e\u043b\u043e\u0433\u0438\u0447\u0435\u0441\u043a\u043e\u0433\u043e \u0438\u043d\u0436\u0438\u043d\u0438\u0440\u0438\u043d\u0433\u0430 \u0432 \u0447\u0430\u0441\u0442\u043d\u043e\u0441\u0442\u0438. \u041f\u0440\u0435\u0434\u043f\u043e\u0441\u044b\u043b\u043a\u043e\u0439 \u043f\u043e\u044f\u0432\u043b\u0435\u043d\u0438\u044f \u043f\u0440\u043e\u0440\u044b\u0432\u043d\u044b\u0445 \u0442\u0435\u0445\u043d\u043e\u043b\u043e\u0433\u0438\u0439, \u043a\u043e\u0442\u043e\u0440\u044b\u0435 \u043f\u043e\u0437\u0432\u043e\u043b\u0438 \u0431\u044b \u0435\u0435 \u0440\u0435\u0448\u0438\u0442\u044c \u0430\u0432\u0442\u043e\u0440 \u0441\u0447\u0438\u0442\u0430\u0435\u0442 \u043f\u043e\u0438\u0441\u043a \u0440\u0435\u0448\u0435\u043d\u0438\u0439 \u043d\u0430 \u043e\u0441\u043d\u043e\u0432\u0435 \u043c\u0435\u0442\u043e\u0434\u043e\u0432 \u0441\u0438\u0441\u0442\u0435\u043c\u043d\u043e\u0433\u043e \u0430\u043d\u0430\u043b\u0438\u0437\u0430, \u043a\u0430\u043a \u0441\u0430\u043c\u043e\u0433\u043e \u043e\u0431\u044a\u0435\u043a\u0442\u0430 \u0438\u0441\u0441\u043b\u0435\u0434\u043e\u0432\u0430\u043d\u0438\u044f \uf02d \u0442\u0435\u043a\u0441\u0442\u0430, \u0442\u0430\u043a \u0438 \u043f\u043e\u0441\u0442\u0430\u0432\u043b\u0435\u043d\u043d\u044b\u0445 \u043f\u0440\u0438\u043a\u043b\u0430\u0434\u043d\u044b\u0445 \u0437\u0430\u0434\u0430\u0447, \u043a\u043e\u0442\u043e\u0440\u044b\u0435 \u0434\u043e\u043b\u0436\u043d\u044b \u0431\u044b\u0442\u044c \u0440\u0435\u0448\u0435\u043d\u044b \u0432 \u0440\u0435\u0437\u0443\u043b\u044c\u0442\u0430\u0442\u0435 \u0442\u0430\u043a\u043e\u0439 \u043e\u0431\u0440\u0430\u0431\u043e\u0442\u043a\u0438. \u0418\u043d\u044b\u043c\u0438 \u0441\u043b\u043e\u0432\u0430\u043c\u0438, \u0434\u043b\u044f \u0441\u0435\u043c\u0430\u043d\u0442\u0438\u0447\u0435\u0441\u043a\u043e\u0433\u043e \u0430\u043d\u0430\u043b\u0438\u0437\u0430 \u0442\u0435\u043a\u0441\u0442\u043e\u0432\u043e\u0439 \u0438\u043d\u0444\u043e\u0440\u043c\u0430\u0446\u0438\u0438 \u0442\u0440\u0435\u0431\u0443\u0435\u0442\u0441\u044f \u043e\u043d\u0442\u043e\u043b\u043e\u0433\u0438\u0447\u0435\u0441\u043a\u0438\u0439 \u043f\u043e\u0434\u0445\u043e\u0434, \u0442.\u0435. \u0447\u0442\u043e\u0431\u044b \u043e\u0431\u043d\u0430\u0440\u0443\u0436\u0438\u0442\u044c \u0432 \u0442\u0435\u043a\u0441\u0442\u0435 \u0442\u0440\u0435\u0431\u0443\u0435\u043c\u0443\u044e \u0438\u043d\u0444\u043e\u0440\u043c\u0430\u0446\u0438\u044e, \u0441\u0430\u043c\u0430 \u0418\u0421 \u0434\u043e\u043b\u0436\u043d\u0430 \u043e\u0431\u043b\u0430\u0434\u0430\u0442\u044c \u0434\u043e\u0441\u0442\u0430\u0442\u043e\u0447\u043d\u044b\u043c \u043e\u0431\u044a\u0435\u043c\u043e\u043c \u043b\u0438\u043d\u0433\u0432\u0438\u0441\u0442\u0438\u0447\u0435\u0441\u043a\u0438\u0445 \u0437\u043d\u0430\u043d\u0438\u0439.", "creator": "Microsoft\u00ae Office Word 2007"}}}